# Class File Format - í´ë˜ìŠ¤ íŒŒì¼ í˜•ì‹

---

## ğŸ¯ í•µì‹¬ ì§ˆë¬¸

ì´ ë¬¸ì„œë¥¼ ì½ê³  ë‚˜ë©´ ë‹¤ìŒ ì§ˆë¬¸ì— ë‹µí•  ìˆ˜ ìˆìŠµë‹ˆë‹¤.

- `.class` íŒŒì¼ì€ ì •í™•íˆ ì–´ë–¤ ë°”ì´ë„ˆë¦¬ êµ¬ì¡°ë¥¼ ê°€ì§€ëŠ”ê°€?
- Magic Number `CAFEBABE`ëŠ” ì™œ í•„ìš”í•˜ë©°, ì–´ë–»ê²Œ ê²€ì¦í•˜ëŠ”ê°€?
- Constant Poolì€ ì™œ í´ë˜ìŠ¤ íŒŒì¼ì˜ ê°€ì¥ ì•ì— ìœ„ì¹˜í•˜ë©°, ì–´ë–»ê²Œ ì¸ë±ì‹±ë˜ëŠ”ê°€?
- `javap -v` ì¶œë ¥ì„ ë³´ê³  ì‹¤ì œ ë°”ì´ë„ˆë¦¬ì™€ ì—°ê²°í•  ìˆ˜ ìˆëŠ”ê°€?
- í´ë˜ìŠ¤ íŒŒì¼ì˜ ë²„ì „ ë²ˆí˜¸ëŠ” ì–´ë–»ê²Œ ê²°ì •ë˜ë©°, JVM í˜¸í™˜ì„±ê³¼ ì–´ë–¤ ê´€ê³„ì¸ê°€?

---

## ğŸ” ì™œ ì´ê²Œ ì¡´ì¬í•˜ëŠ”ê°€

### ë¬¸ì œ: Java ì†ŒìŠ¤ ì½”ë“œë¥¼ ì–´ë–»ê²Œ í”Œë«í¼ ë…ë¦½ì ìœ¼ë¡œ ì‹¤í–‰í•˜ëŠ”ê°€

```
ì „í†µì  ì»´íŒŒì¼ ì–¸ì–´ (C/C++):
  source.c â†’ gcc â†’ machine code (x86, ARM, ...)
  â†’ í”Œë«í¼ ì¢…ì†ì 
  â†’ Windows .exeëŠ” Linuxì—ì„œ ì‹¤í–‰ ë¶ˆê°€

Javaì˜ ì ‘ê·¼:
  source.java â†’ javac â†’ bytecode (.class)
  â†’ JVMì´ bytecode í•´ì„
  â†’ ì–´ë–¤ í”Œë«í¼ì´ë“  JVMë§Œ ìˆìœ¼ë©´ ì‹¤í–‰
  
  "Write Once, Run Anywhere"
```

`.class` íŒŒì¼ì€ JVMì´ ì½ì„ ìˆ˜ ìˆëŠ” **í‘œì¤€í™”ëœ ë°”ì´ë„ˆë¦¬ í˜•ì‹**ì´ë‹¤.

---

## ğŸ“ ë‚´ë¶€ êµ¬ì¡°

### 1. í´ë˜ìŠ¤ íŒŒì¼ ì „ì²´ êµ¬ì¡°

```
ClassFile {
    u4             magic;              // 0xCAFEBABE
    u2             minor_version;      // ë¶€ ë²„ì „
    u2             major_version;      // ì£¼ ë²„ì „
    u2             constant_pool_count;
    cp_info        constant_pool[constant_pool_count-1];
    u2             access_flags;       // public, final, abstract ë“±
    u2             this_class;         // Constant Pool ì¸ë±ìŠ¤
    u2             super_class;        // ë¶€ëª¨ í´ë˜ìŠ¤
    u2             interfaces_count;
    u2             interfaces[interfaces_count];
    u2             fields_count;
    field_info     fields[fields_count];
    u2             methods_count;
    method_info    methods[methods_count];
    u2             attributes_count;
    attribute_info attributes[attributes_count];
}

u1 = unsigned 1 byte
u2 = unsigned 2 bytes
u4 = unsigned 4 bytes
```

---

### 2. Magic Numberì™€ ë²„ì „

```
ì²« 8ë°”ì´íŠ¸:

Offset   Bytes         ì˜ë¯¸
0x00     CA FE BA BE   Magic Number (í´ë˜ìŠ¤ íŒŒì¼ ì‹ë³„)
0x04     00 00         Minor Version
0x06     00 34         Major Version (0x34 = 52 = Java 8)

ë²„ì „ ë§¤í•‘:
  45 (0x2D) = Java 1.1
  46 (0x2E) = Java 1.2
  47 (0x2F) = Java 1.3
  48 (0x30) = Java 1.4
  49 (0x31) = Java 5
  50 (0x32) = Java 6
  51 (0x33) = Java 7
  52 (0x34) = Java 8
  53 (0x35) = Java 9
  ...
  61 (0x3D) = Java 17
  65 (0x41) = Java 21

í˜¸í™˜ì„±:
  JVMì€ ìì‹ ì˜ ë²„ì „ ì´í•˜ í´ë˜ìŠ¤ë§Œ ì‹¤í–‰ ê°€ëŠ¥
  Java 17 JVM: ë²„ì „ 61 ì´í•˜ í´ë˜ìŠ¤ ì‹¤í–‰ OK
  Java 8 JVM:  ë²„ì „ 53 ì´ìƒ í´ë˜ìŠ¤ ì‹¤í–‰ ë¶ˆê°€
  â†’ java.lang.UnsupportedClassVersionError
```

---

### 3. Constant Pool â€” ëª¨ë“  ì‹¬ë³¼ë¦­ ì°¸ì¡°ì˜ ì €ì¥ì†Œ

```
Constant Pool êµ¬ì¡°:

constant_pool_count: 3ë°”ì´íŠ¸ ì •ìˆ˜ (ì˜ˆ: 30)
â†’ ì‹¤ì œ ì—”íŠ¸ë¦¬ëŠ” constant_pool[1] ~ constant_pool[29]
â†’ ì¸ë±ìŠ¤ 0ì€ null ì˜ë¯¸ë¡œ ì˜ˆì•½

Constant Pool Entry íƒ€ì… (ì¼ë¶€):

CONSTANT_Utf8 (tag=1)
  - ë¬¸ìì—´ ë°ì´í„° (í´ë˜ìŠ¤ëª…, í•„ë“œëª…, ë©”ì„œë“œëª… ë“±)
  
CONSTANT_Integer (tag=3)
  - int ë¦¬í„°ëŸ´

CONSTANT_Float (tag=4)
  - float ë¦¬í„°ëŸ´

CONSTANT_Long (tag=5)
  - long ë¦¬í„°ëŸ´ (2ê°œ ìŠ¬ë¡¯ ì°¨ì§€)

CONSTANT_Double (tag=6)
  - double ë¦¬í„°ëŸ´ (2ê°œ ìŠ¬ë¡¯ ì°¨ì§€)

CONSTANT_Class (tag=7)
  - í´ë˜ìŠ¤/ì¸í„°í˜ì´ìŠ¤ ì°¸ì¡°
  - name_index â†’ CONSTANT_Utf8

CONSTANT_String (tag=8)
  - String ë¦¬í„°ëŸ´
  - string_index â†’ CONSTANT_Utf8

CONSTANT_Fieldref (tag=9)
  - í•„ë“œ ì°¸ì¡°
  - class_index â†’ CONSTANT_Class
  - name_and_type_index â†’ CONSTANT_NameAndType

CONSTANT_Methodref (tag=10)
  - ë©”ì„œë“œ ì°¸ì¡°
  
CONSTANT_InterfaceMethodref (tag=11)
  - ì¸í„°í˜ì´ìŠ¤ ë©”ì„œë“œ ì°¸ì¡°

CONSTANT_NameAndType (tag=12)
  - ì´ë¦„ê³¼ íƒ€ì… ë””ìŠ¤í¬ë¦½í„°
  - name_index â†’ CONSTANT_Utf8
  - descriptor_index â†’ CONSTANT_Utf8
```

#### Constant Pool ì˜ˆì‹œ

```java
public class Example {
    public void hello() {
        System.out.println("Hello");
    }
}
```

```
Constant Pool:
   #1 = Methodref    #6.#15   // java/lang/Object."<init>":()V
   #2 = Fieldref     #16.#17  // java/lang/System.out:Ljava/io/PrintStream;
   #3 = String       #18      // Hello
   #4 = Methodref    #19.#20  // java/io/PrintStream.println:(Ljava/lang/String;)V
   #5 = Class        #21      // Example
   #6 = Class        #22      // java/lang/Object
   ...
  #15 = NameAndType  #23:#24  // "<init>":()V
  #16 = Class        #25      // java/lang/System
  #17 = NameAndType  #26:#27  // out:Ljava/io/PrintStream;
  #18 = Utf8         Hello
  #19 = Class        #28      // java/io/PrintStream
  #20 = NameAndType  #29:#30  // println:(Ljava/lang/String;)V
  #21 = Utf8         Example
  #22 = Utf8         java/lang/Object
  #23 = Utf8         <init>
  #24 = Utf8         ()V
  #25 = Utf8         java/lang/System
  #26 = Utf8         out
  #27 = Utf8         Ljava/io/PrintStream;
  #28 = Utf8         java/io/PrintStream
  #29 = Utf8         println
  #30 = Utf8         (Ljava/lang/String;)V

ì¸ë±ìŠ¤ ì²´ì¸:
  #4 (Methodref) â†’ #19 (Class) + #20 (NameAndType)
    â†’ #19 â†’ #28 (Utf8 "java/io/PrintStream")
    â†’ #20 â†’ #29 (Utf8 "println") + #30 (Utf8 "(Ljava/lang/String;)V")
```

---

### 4. Access Flags

```
í´ë˜ìŠ¤ Access Flags (ë¹„íŠ¸ ë§ˆìŠ¤í¬):

ACC_PUBLIC     = 0x0001   // public
ACC_FINAL      = 0x0010   // final
ACC_SUPER      = 0x0020   // invokespecial ì˜ë¯¸ë¡  (í•­ìƒ ì„¤ì •)
ACC_INTERFACE  = 0x0200   // interface
ACC_ABSTRACT   = 0x0400   // abstract
ACC_SYNTHETIC  = 0x1000   // ì»´íŒŒì¼ëŸ¬ ìƒì„±
ACC_ANNOTATION = 0x2000   // @interface
ACC_ENUM       = 0x4000   // enum

ì˜ˆ:
  public class Foo            â†’ 0x0021 (PUBLIC | SUPER)
  public final class Bar      â†’ 0x0031 (PUBLIC | FINAL | SUPER)
  public interface Baz        â†’ 0x0601 (PUBLIC | INTERFACE | ABSTRACT)
  public enum Status          â†’ 0x4031 (PUBLIC | FINAL | SUPER | ENUM)
```

---

### 5. Fieldsì™€ Methods

```
field_info {
    u2             access_flags;    // public, static, final ë“±
    u2             name_index;      // Constant Pool â†’ í•„ë“œëª…
    u2             descriptor_index; // íƒ€ì… ë””ìŠ¤í¬ë¦½í„°
    u2             attributes_count;
    attribute_info attributes[attributes_count];
}

method_info {
    u2             access_flags;
    u2             name_index;
    u2             descriptor_index;
    u2             attributes_count;
    attribute_info attributes[attributes_count]; // Code, Exceptions ë“±
}

ë””ìŠ¤í¬ë¦½í„° (Type Descriptor):
  B = byte
  C = char
  D = double
  F = float
  I = int
  J = long
  S = short
  Z = boolean
  L<classname>; = ì°¸ì¡° íƒ€ì…
  [<type> = ë°°ì—´

ì˜ˆ:
  int x;                 â†’ descriptor: I
  String name;           â†’ descriptor: Ljava/lang/String;
  int[] arr;             â†’ descriptor: [I
  void foo(int, String)  â†’ descriptor: (ILjava/lang/String;)V
  Object bar(int[][])    â†’ descriptor: ([[I)Ljava/lang/Object;
```

---

### 6. Code Attribute â€” ë©”ì„œë“œ ë°”ì´íŠ¸ì½”ë“œ ì €ì¥

```
Code_attribute {
    u2 attribute_name_index;  // "Code"
    u4 attribute_length;
    u2 max_stack;             // Operand Stack ìµœëŒ€ ê¹Šì´
    u2 max_locals;            // Local Variable Array í¬ê¸°
    u4 code_length;
    u1 code[code_length];     // ì‹¤ì œ ë°”ì´íŠ¸ì½”ë“œ
    u2 exception_table_length;
    {   u2 start_pc;
        u2 end_pc;
        u2 handler_pc;
        u2 catch_type;
    } exception_table[exception_table_length];
    u2 attributes_count;
    attribute_info attributes[attributes_count];
}

ì˜ˆ:
  public int add(int a, int b) {
      return a + b;
  }

Code:
  max_stack=2, max_locals=3 (this, a, b)
  0: iload_1      // LVA[1](a)ì„ ìŠ¤íƒì— push
  1: iload_2      // LVA[2](b)ì„ ìŠ¤íƒì— push
  2: iadd         // ë‘ ê°’ì„ pop, ë”í•œ í›„ push
  3: ireturn      // ìŠ¤íƒ top ê°’ì„ ë°˜í™˜
```

---

## ğŸ’» ì‹¤í—˜ìœ¼ë¡œ í™•ì¸í•˜ê¸°

### ì‹¤í—˜ 1: ë°”ì´ë„ˆë¦¬ ì§ì ‘ ë¶„ì„ (hexdump)

```java
public class Simple {
    public static void main(String[] args) {
        System.out.println("Hello");
    }
}
```

```bash
javac Simple.java
hexdump -C Simple.class | head -20

# ì¶œë ¥:
# 00000000  ca fe ba be 00 00 00 34  00 1d 0a 00 06 00 0f 09  |.......4........|
#           ^^^^^^^^^^^ Magic       ^^^^^ Minor  ^^^^^ Major (52 = Java 8)
#                                         ^^^^^ Constant Pool Count (29)
# 00000010  00 10 00 11 08 00 12 0a  00 13 00 14 07 00 15 07  |................|
# ...
```

---

### ì‹¤í—˜ 2: javapë¡œ ë””ìŠ¤ì–´ì…ˆë¸”

```bash
javap -v Simple.class

# ì¶œë ¥:
# public class Simple
#   minor version: 0
#   major version: 52
#   flags: ACC_PUBLIC, ACC_SUPER
# Constant pool:
#    #1 = Methodref          #6.#15
#    #2 = Fieldref           #16.#17
#    #3 = String             #18
#    #4 = Methodref          #19.#20
#    #5 = Class              #21
#    ...
#   #18 = Utf8               Hello
#   ...
# {
#   public static void main(java.lang.String[]);
#     descriptor: ([Ljava/lang/String;)V
#     flags: ACC_PUBLIC, ACC_STATIC
#     Code:
#       stack=2, locals=1, args_size=1
#          0: getstatic     #2    // Field java/lang/System.out:Ljava/io/PrintStream;
#          3: ldc           #3    // String Hello
#          5: invokevirtual #4    // Method java/io/PrintStream.println:(Ljava/lang/String;)V
#          8: return
# }
```

---

### ì‹¤í—˜ 3: í´ë˜ìŠ¤ íŒŒì¼ ë¦¬ë” êµ¬í˜„

```java
import java.io.*;

public class ClassFileReader {
    public static void main(String[] args) throws Exception {
        DataInputStream in = new DataInputStream(
            new FileInputStream("Simple.class"));
        
        // Magic Number
        int magic = in.readInt();
        System.out.printf("Magic: 0x%X%n", magic);
        if (magic != 0xCAFEBABE) {
            throw new IOException("Invalid class file");
        }
        
        // Version
        int minor = in.readUnsignedShort();
        int major = in.readUnsignedShort();
        System.out.printf("Version: %d.%d (Java %s)%n", 
            major, minor, getJavaVersion(major));
        
        // Constant Pool Count
        int cpCount = in.readUnsignedShort();
        System.out.printf("Constant Pool Count: %d%n", cpCount);
        
        // Constant Pool Entries
        for (int i = 1; i < cpCount; i++) {
            int tag = in.readUnsignedByte();
            System.out.printf("#%d = tag %d%n", i, tag);
            
            switch (tag) {
                case 1: // CONSTANT_Utf8
                    int len = in.readUnsignedShort();
                    byte[] bytes = new byte[len];
                    in.readFully(bytes);
                    System.out.printf("     Utf8: %s%n", new String(bytes));
                    break;
                case 7: // CONSTANT_Class
                    int nameIndex = in.readUnsignedShort();
                    System.out.printf("     Class: #%d%n", nameIndex);
                    break;
                // ... ë‹¤ë¥¸ íƒ€ì… ì²˜ë¦¬
                default:
                    throw new IOException("Unknown tag: " + tag);
            }
        }
        
        in.close();
    }
    
    static String getJavaVersion(int major) {
        return major >= 45 ? "1." + (major - 44) : "Unknown";
    }
}
```

---

### ì‹¤í—˜ 4: ASMìœ¼ë¡œ í´ë˜ìŠ¤ íŒŒì¼ ì½ê¸°

```java
// ASM ë¼ì´ë¸ŒëŸ¬ë¦¬ ì‚¬ìš© (gradle/maven ì˜ì¡´ì„± í•„ìš”)
import org.objectweb.asm.*;
import java.io.FileInputStream;

public class ASMReader {
    public static void main(String[] args) throws Exception {
        ClassReader reader = new ClassReader(
            new FileInputStream("Simple.class"));
        
        reader.accept(new ClassVisitor(Opcodes.ASM9) {
            @Override
            public void visit(int version, int access, String name, 
                              String signature, String superName, String[] interfaces) {
                System.out.println("Class: " + name);
                System.out.println("Super: " + superName);
                System.out.println("Version: " + version);
            }
            
            @Override
            public MethodVisitor visitMethod(int access, String name, 
                                             String descriptor, String signature, String[] exceptions) {
                System.out.println("Method: " + name + descriptor);
                return null;
            }
            
            @Override
            public FieldVisitor visitField(int access, String name, 
                                          String descriptor, String signature, Object value) {
                System.out.println("Field: " + name + ":" + descriptor);
                return null;
            }
        }, 0);
    }
}
```

---

## âš¡ ì‹¤ë¬´ ì„íŒ©íŠ¸

### í´ë˜ìŠ¤ íŒŒì¼ ë²„ì „ í˜¸í™˜ì„± ë¬¸ì œ í•´ê²°

```
ë¬¸ì œ:
  ê°œë°œ: Java 17
  ìš´ì˜: Java 8
  â†’ java.lang.UnsupportedClassVersionError: ... (class file version 61.0)

í•´ê²°ì±… 1: --release í”Œë˜ê·¸
  javac --release 8 MyClass.java
  â†’ Java 8 í˜¸í™˜ ë°”ì´íŠ¸ì½”ë“œ ìƒì„± (major version 52)

í•´ê²°ì±… 2: target ì˜µì…˜
  javac -source 8 -target 8 MyClass.java
  (Deprecated in Java 9+)

Gradle:
  compileJava {
      options.release = 8
  }

Maven:
  <maven.compiler.release>8</maven.compiler.release>
```

### ë‚œë…í™”ì™€ í´ë˜ìŠ¤ íŒŒì¼ ê²€ì¦

```
ë‚œë…í™” ë„êµ¬ (ProGuard, R8):
  - í´ë˜ìŠ¤ëª…, ë©”ì„œë“œëª…, í•„ë“œëª…ì„ ì§§ê²Œ ë³€ê²½
  - Constant Poolì˜ Utf8 ì—”íŠ¸ë¦¬ ìˆ˜ì •
  - ì‚¬ìš©í•˜ì§€ ì•ŠëŠ” ì½”ë“œ ì œê±°
  
ê²€ì¦:
  JVMì€ í´ë˜ìŠ¤ ë¡œë”© ì‹œ Bytecode Verifier ì‹¤í–‰
  - Constant Pool ë¬´ê²°ì„± í™•ì¸
  - íƒ€ì… ì•ˆì „ì„± ê²€ì¦
  - ìŠ¤íƒ/ë¡œì»¬ ë³€ìˆ˜ ì ‘ê·¼ ë²”ìœ„ í™•ì¸
  
  ì˜ëª»ëœ ë‚œë…í™” â†’ VerifyError
```

### JAR ì„œëª…ê³¼ í´ë˜ìŠ¤ íŒŒì¼ ë¬´ê²°ì„±

```
JAR ì„œëª…:
  jarsigner -keystore mystore.jks myapp.jar mykey

ì„œëª… ê²€ì¦ ê³¼ì •:
  1. META-INF/MANIFEST.MF ì½ê¸°
     ê° .class íŒŒì¼ì˜ SHA-256 í•´ì‹œ ì €ì¥
  
  2. í´ë˜ìŠ¤ ë¡œë”© ì‹œ í•´ì‹œ ì¬ê³„ì‚°
     ì‹¤ì œ íŒŒì¼ ë‚´ìš©ê³¼ MANIFEST ë¹„êµ
  
  3. ë¶ˆì¼ì¹˜ ì‹œ SecurityException
     â†’ ë³€ì¡° ê°ì§€

í´ë˜ìŠ¤ íŒŒì¼ êµ¬ì¡° ì§€ì‹ì´ í•„ìš”í•œ ì´ìœ :
  ìˆ˜ë™ ê²€ì¦, ì»¤ìŠ¤í…€ ClassLoader êµ¬í˜„ ì‹œ í•„ìˆ˜
```

---

## ğŸš« í”í•œ ì˜¤í•´

### "í´ë˜ìŠ¤ íŒŒì¼ ë²„ì „ì€ JDK ë²„ì „ê³¼ í•­ìƒ ë™ì¼í•˜ë‹¤"

```
âŒ ì˜ëª»ëœ ì´í•´:
  Java 8ë¡œ ì»´íŒŒì¼í•˜ë©´ í´ë˜ìŠ¤ íŒŒì¼ ë²„ì „ì€ í•­ìƒ 52ë‹¤.

âœ… ì‹¤ì œ:
  javac --release ì˜µì…˜ìœ¼ë¡œ í•˜ìœ„ ë²„ì „ ìƒì„± ê°€ëŠ¥
  
  javac --release 7 MyClass.java
  â†’ major version 51 (Java 7)
  
  Java 8 JDKë¡œ Java 7 í˜¸í™˜ í´ë˜ìŠ¤ ìƒì„±
  â†’ í•˜ìœ„ í˜¸í™˜ì„± ë³´ì¥
  
  ë‹¨, ìƒˆ ë¬¸ë²•(ëŒë‹¤ ë“±)ì€ ì‚¬ìš© ë¶ˆê°€
```

### "Constant Pool ì¸ë±ìŠ¤ëŠ” 0ë¶€í„° ì‹œì‘í•œë‹¤"

```
âŒ ì˜ëª»ëœ ì´í•´:
  constant_pool[0]ì´ ì²« ë²ˆì§¸ ì—”íŠ¸ë¦¬ë‹¤.

âœ… ì‹¤ì œ:
  constant_pool[1]ì´ ì²« ë²ˆì§¸ ì—”íŠ¸ë¦¬
  
  ì´ìœ :
  - ì¸ë±ìŠ¤ 0ì€ "no reference" ì˜ë¯¸ë¡œ ì˜ˆì•½
  - super_classê°€ ì—†ëŠ” java.lang.ObjectëŠ” super_class=0
  
  constant_pool_count = 30ì´ë©´
  â†’ ì‹¤ì œ ì—”íŠ¸ë¦¬: constant_pool[1] ~ constant_pool[29]
  â†’ ì´ 29ê°œ ì—”íŠ¸ë¦¬
```

### "í´ë˜ìŠ¤ íŒŒì¼ì€ í…ìŠ¤íŠ¸ ì—ë””í„°ë¡œ ì½ì„ ìˆ˜ ìˆë‹¤"

```
âŒ ì˜ëª»ëœ ì´í•´:
  .class íŒŒì¼ì„ í…ìŠ¤íŠ¸ ì—ë””í„°ë¡œ ì—´ë©´ ì½”ë“œë¥¼ ë³¼ ìˆ˜ ìˆë‹¤.

âœ… ì‹¤ì œ:
  .class íŒŒì¼ì€ ë°”ì´ë„ˆë¦¬ í˜•ì‹
  â†’ í…ìŠ¤íŠ¸ ì—ë””í„°ë¡œ ì—´ë©´ ê¹¨ì§„ ë¬¸ì (binary garbage)
  
  ë¶„ì„ ë„êµ¬:
  - javap (JDK ê¸°ë³¸ ì œê³µ)
  - hexdump, xxd (ë°”ì´ë„ˆë¦¬ ë·°ì–´)
  - JD-GUI, CFR (ë””ì»´íŒŒì¼ëŸ¬)
  - ASM, Javassist (ë¼ì´ë¸ŒëŸ¬ë¦¬)
```

---

## ğŸ“Œ í•µì‹¬ ì •ë¦¬

```
í´ë˜ìŠ¤ íŒŒì¼ êµ¬ì¡°
  Magic Number (CA FE BA BE)
  Version (Minor + Major)
  Constant Pool (ì‹¬ë³¼ë¦­ ì°¸ì¡° ì €ì¥ì†Œ)
  Access Flags (public, final ë“±)
  This/Super Class (í´ë˜ìŠ¤ ì •ë³´)
  Interfaces (êµ¬í˜„ ì¸í„°í˜ì´ìŠ¤)
  Fields (í•„ë“œ ëª©ë¡)
  Methods (ë©”ì„œë“œ ëª©ë¡ + Code ì†ì„±)
  Attributes (ì¶”ê°€ ì •ë³´)

Constant Pool
  ì¸ë±ìŠ¤ 1ë¶€í„° ì‹œì‘ (0ì€ ì˜ˆì•½)
  Utf8, Class, String, Methodref ë“±
  ëª¨ë“  ì‹¬ë³¼ë¦­ ì°¸ì¡°ì˜ ì¤‘ì•™ ì €ì¥ì†Œ

ë²„ì „ í˜¸í™˜ì„±
  Major Version: JDK ë²„ì „ ê²°ì • (52 = Java 8)
  JVMì€ ìì‹ ì˜ ë²„ì „ ì´í•˜ í´ë˜ìŠ¤ë§Œ ì‹¤í–‰
  --release ì˜µì…˜ìœ¼ë¡œ í•˜ìœ„ í˜¸í™˜ ë°”ì´íŠ¸ì½”ë“œ ìƒì„±

ë””ìŠ¤í¬ë¦½í„°
  íƒ€ì… í‘œí˜„: I (int), J (long), L...; (ê°ì²´)
  ë©”ì„œë“œ: (ë§¤ê°œë³€ìˆ˜)ë°˜í™˜íƒ€ì…

Code Attribute
  max_stack: Operand Stack ìµœëŒ€ ê¹Šì´
  max_locals: Local Variable Array í¬ê¸°
  code[]: ì‹¤ì œ ë°”ì´íŠ¸ì½”ë“œ

ë¶„ì„ ë„êµ¬
  javap -v: ë””ìŠ¤ì–´ì…ˆë¸” (ê°€ì¥ ê¸°ë³¸)
  hexdump: ë°”ì´ë„ˆë¦¬ ì§ì ‘ í™•ì¸
  ASM: í”„ë¡œê·¸ë˜ë° ë°©ì‹ ë¶„ì„/ì¡°ì‘
```

---

## ğŸ¤” ìƒê°í•´ë³¼ ë¬¸ì œ

**Q1.** ë‹¤ìŒ ë©”ì„œë“œì˜ ë””ìŠ¤í¬ë¦½í„°ë¥¼ ì‘ì„±í•˜ë¼. `List<String> process(int[] arr, Map<String, Integer> map)`

**Q2.** Constant Poolì´ ì™œ í´ë˜ìŠ¤ íŒŒì¼ì˜ ì•ìª½ì— ìœ„ì¹˜í•˜ëŠ”ê°€? Fields, Methods ë‹¤ìŒì— ìˆìœ¼ë©´ ì•ˆ ë˜ëŠ” ì´ìœ ë¥¼ ì„¤ëª…í•˜ë¼.

**Q3.** Java 17ë¡œ ì»´íŒŒì¼í•œ í´ë˜ìŠ¤ë¥¼ Java 8 JVMì—ì„œ ì‹¤í–‰í•˜ë ¤ë©´ ì–´ë–»ê²Œ í•´ì•¼ í•˜ëŠ”ê°€? ê°€ëŠ¥í•œ ë°©ë²•ê³¼ ì œì•½ì‚¬í•­ì„ ì„¤ëª…í•˜ë¼.

> ğŸ’¡ **í•´ì„¤**
>
> **Q1.** `([ILjava/util/Map;)Ljava/util/List;`. ì„¤ëª…: ë§¤ê°œë³€ìˆ˜ ë¶€ë¶„ `[I` (int ë°°ì—´) + `Ljava/util/Map;` (Map ê°ì²´, ì œë„¤ë¦­ì€ erasureë¡œ ì†Œê±°). ë°˜í™˜ íƒ€ì… `Ljava/util/List;` (List ê°ì²´). ì œë„¤ë¦­ íƒ€ì… ì •ë³´ `<String>`, `<String, Integer>`ëŠ” ë°”ì´íŠ¸ì½”ë“œì—ì„œ ì‚¬ë¼ì§€ê³  Signature ì†ì„±ì—ë§Œ ë‚¨ëŠ”ë‹¤ (ë””ìŠ¤í¬ë¦½í„°ì—ëŠ” ì—†ìŒ).
>
> **Q2.** Constant Poolì´ ì•ì— ìˆëŠ” ì´ìœ : Fields, Methods, Attributesê°€ ëª¨ë‘ Constant Poolì˜ ì¸ë±ìŠ¤ë¥¼ ì°¸ì¡°í•˜ê¸° ë•Œë¬¸ì´ë‹¤. íŒŒì¼ì„ ìˆœì°¨ ì½ê¸°í•  ë•Œ Constant Poolì„ ë¨¼ì € ë©”ëª¨ë¦¬ì— ë¡œë“œí•´ì•¼ ì´í›„ ë°ì´í„°(í•„ë“œëª…, ë©”ì„œë“œëª…, íƒ€ì…)ë¥¼ í•´ì„í•  ìˆ˜ ìˆë‹¤. ë§Œì•½ ë’¤ì— ìˆë‹¤ë©´ íŒŒì¼ì„ ë‘ ë²ˆ ì½ê±°ë‚˜ ëœë¤ ì•¡ì„¸ìŠ¤ê°€ í•„ìš”í•´ ì„±ëŠ¥ ì €í•˜. ë˜í•œ Constant Pool Countê°€ ìˆì–´ì•¼ ë‚˜ë¨¸ì§€ ë°ì´í„°ë¥¼ íŒŒì‹±í•  ì˜¤í”„ì…‹ì„ ê³„ì‚°í•  ìˆ˜ ìˆë‹¤.
>
> **Q3.** ë°©ë²• 1: `javac --release 8 MyClass.java`ë¡œ Java 8 í˜¸í™˜ ë°”ì´íŠ¸ì½”ë“œ (major version 52) ìƒì„±. ì œì•½: Java 9+ ì‹ ê·œ ë¬¸ë²•/API ì‚¬ìš© ë¶ˆê°€ (ëŒë‹¤, ìŠ¤íŠ¸ë¦¼ OK, ëª¨ë“ˆì€ X). ë°©ë²• 2: Retrolambda ê°™ì€ ë„êµ¬ë¡œ ë°”ì´íŠ¸ì½”ë“œë¥¼ ë‹¤ìš´ê·¸ë ˆì´ë“œ. ë°©ë²• 3: ì´ë¯¸ ì»´íŒŒì¼ëœ í´ë˜ìŠ¤ë¼ë©´ ë¶ˆê°€ëŠ¥ â€” JVM ë²„ì „ì„ ì˜¬ë¦¬ê±°ë‚˜ ì¬ì»´íŒŒì¼ í•„ìš”. í•µì‹¬: í´ë˜ìŠ¤ íŒŒì¼ ë²„ì „ì€ ì»´íŒŒì¼ ì‹œì ì— ê²°ì •ë˜ê³ , ëŸ°íƒ€ì„ì— ë³€ê²½ ë¶ˆê°€.

---

## ğŸ“š ì°¸ê³  ìë£Œ

- [JVMS Chapter 4 â€” The class File Format](https://docs.oracle.com/javase/specs/jvms/se21/html/jvms-4.html)
- [ASM Bytecode Manipulation Framework](https://asm.ow2.io/)
- [JVM Class File Disassembler (javap)](https://docs.oracle.com/en/java/javase/17/docs/specs/man/javap.html)

---

<div align="center">

**[â¬…ï¸ ì´ì „: Off-Heap & Direct Memory](../runtime-data-areas/07-off-heap-direct-memory.md)** | **[ë‹¤ìŒ: Bytecode Instruction Set â¡ï¸](./02-bytecode-instruction-set.md)**

</div>
