# Bytecode Instruction Set - ë°”ì´íŠ¸ì½”ë“œ ëª…ë ¹ì–´ ì§‘í•©

---

## ğŸ¯ í•µì‹¬ ì§ˆë¬¸

ì´ ë¬¸ì„œë¥¼ ì½ê³  ë‚˜ë©´ ë‹¤ìŒ ì§ˆë¬¸ì— ë‹µí•  ìˆ˜ ìˆìŠµë‹ˆë‹¤.

- JVM ë°”ì´íŠ¸ì½”ë“œëŠ” ì´ ëª‡ ê°œì˜ ëª…ë ¹ì–´ë¡œ êµ¬ì„±ë˜ë©°, ì–´ë–»ê²Œ ë¶„ë¥˜ë˜ëŠ”ê°€?
- `iload`, `fload`, `aload`ì²˜ëŸ¼ íƒ€ì…ë³„ë¡œ ëª…ë ¹ì–´ê°€ ë¶„ë¦¬ëœ ì´ìœ ëŠ” ë¬´ì—‡ì¸ê°€?
- `iconst_1`ê³¼ `bipush 1`ì˜ ì°¨ì´ëŠ” ë¬´ì—‡ì´ë©°, ì–¸ì œ ì–´ëŠ ê²ƒì„ ì‚¬ìš©í•˜ëŠ”ê°€?
- ë°”ì´íŠ¸ì½”ë“œëŠ” ì™œ ìŠ¤íƒ ê¸°ë°˜ì´ë©°, í”¼ì—°ì‚°ìëŠ” ì–´ë””ì„œ ì˜¤ëŠ”ê°€?
- `javap -c`ë¡œ ë³¸ ë°”ì´íŠ¸ì½”ë“œì™€ ì‹¤ì œ ë°”ì´ë„ˆë¦¬ì˜ ê´€ê³„ëŠ”?

---

## ğŸ” ì™œ ì´ê²Œ ì¡´ì¬í•˜ëŠ”ê°€

### ë¬¸ì œ: Java ì†ŒìŠ¤ ì½”ë“œë¥¼ ì–´ë–¤ ì¤‘ê°„ ì–¸ì–´ë¡œ ë³€í™˜í•  ê²ƒì¸ê°€

```java
int sum = a + b;
```

```
ê¸°ê³„ì–´ë¡œ ì§ì ‘ ì»´íŒŒì¼ (C/C++ ë°©ì‹):
  mov eax, [a]
  add eax, [b]
  mov [sum], eax
  â†’ CPU ì¢…ì†ì  (x86, ARMë§ˆë‹¤ ë‹¤ë¦„)

JVMì˜ ì ‘ê·¼: í”Œë«í¼ ë…ë¦½ì  ì¤‘ê°„ ì–¸ì–´
  iload_1      // aë¥¼ ìŠ¤íƒì— push
  iload_2      // bë¥¼ ìŠ¤íƒì— push
  iadd         // ë‘ ê°’ì„ pop, ë”í•œ í›„ push
  istore_3     // ê²°ê³¼ë¥¼ sumì— ì €ì¥
  
  â†’ ì–´ë–¤ CPUë“  JVMë§Œ êµ¬í˜„í•˜ë©´ ì‹¤í–‰ ê°€ëŠ¥
```

ë°”ì´íŠ¸ì½”ë“œëŠ” **ì¶”ìƒí™”ëœ ê¸°ê³„ì–´**ë‹¤.

---

## ğŸ“ ë‚´ë¶€ êµ¬ì¡°

### 1. ë°”ì´íŠ¸ì½”ë“œ ëª…ë ¹ì–´ ê°œìš”

```
ì´ ëª…ë ¹ì–´ ìˆ˜: ì•½ 200ê°œ (opcode 0x00 ~ 0xC9)

ëª…ë ¹ì–´ í˜•ì‹:
  opcode [operand1] [operand2] ...
  
  ì˜ˆ:
  0x10 0x2A        â†’ bipush 42 (opcode=0x10, operand=0x2A=42)
  0x59             â†’ dup (opcode=0x59, operand ì—†ìŒ)

opcode í¬ê¸°: 1 byte
  â†’ ìµœëŒ€ 256ê°œ ëª…ë ¹ì–´ ê°€ëŠ¥
  â†’ ì‹¤ì œ ì‚¬ìš©: ~200ê°œ
```

---

### 2. ëª…ë ¹ì–´ ë¶„ë¥˜ (ì¹´í…Œê³ ë¦¬ë³„)

```
1. Load & Store (LVA â†” Operand Stack)
   iload, istore, aload, astore, ...
   
2. Arithmetic (ì‚°ìˆ  ì—°ì‚°)
   iadd, isub, imul, idiv, irem, ...
   
3. Type Conversion (íƒ€ì… ë³€í™˜)
   i2l, l2i, f2d, d2i, ...
   
4. Stack Manipulation (ìŠ¤íƒ ì¡°ì‘)
   pop, dup, swap, ...
   
5. Control Flow (ì œì–´ íë¦„)
   if_icmpeq, goto, ifeq, ifne, ...
   
6. Method Invocation (ë©”ì„œë“œ í˜¸ì¶œ)
   invokevirtual, invokestatic, invokespecial, ...
   
7. Object Operations (ê°ì²´ ì—°ì‚°)
   new, newarray, getfield, putfield, ...
   
8. Return
   ireturn, areturn, return, ...
```

---

### 3. íƒ€ì…ë³„ ëª…ë ¹ì–´ ë¶„ë¦¬

```
ì™œ iload, fload, aloadê°€ ë”°ë¡œ ì¡´ì¬í•˜ëŠ”ê°€?

JVMì€ íƒ€ì… ì•ˆì „ì„±ì„ ë°”ì´íŠ¸ì½”ë“œ ìˆ˜ì¤€ì—ì„œ ë³´ì¥

int ì—°ì‚°:
  iload   â†’ int load
  istore  â†’ int store
  iadd    â†’ int add
  
float ì—°ì‚°:
  fload   â†’ float load
  fstore  â†’ float store
  fadd    â†’ float add

reference ì—°ì‚°:
  aload   â†’ reference load (array, object)
  astore  â†’ reference store

íƒ€ì… ì ‘ë‘ì‚¬:
  i = int
  l = long
  f = float
  d = double
  a = reference (address)
  b = byte
  c = char
  s = short

ì´ì :
  1. Bytecode Verifierê°€ íƒ€ì… ì˜¤ë¥˜ ê²€ì¶œ
  2. JIT ì»´íŒŒì¼ëŸ¬ì˜ ìµœì í™” íŒíŠ¸
  3. ëª…ë ¹ì–´ë§Œ ë³´ê³  í”¼ì—°ì‚°ì íƒ€ì… íŒŒì•… ê°€ëŠ¥
```

---

### 4. ìƒìˆ˜ ë¡œë“œ ëª…ë ¹ì–´ ìµœì í™”

```
int ìƒìˆ˜ë¥¼ ë¡œë“œí•˜ëŠ” ì—¬ëŸ¬ ë°©ë²•:

iconst_m1    â†’ -1
iconst_0     â†’ 0
iconst_1     â†’ 1
iconst_2     â†’ 2
iconst_3     â†’ 3
iconst_4     â†’ 4
iconst_5     â†’ 5

bipush <n>   â†’ -128 ~ 127
sipush <n>   â†’ -32768 ~ 32767
ldc <index>  â†’ Constant Pool[index] (int, float, String, ...)

ì˜ˆ:
  int a = 0;      â†’ iconst_0 (1 byte)
  int b = 100;    â†’ bipush 100 (2 bytes)
  int c = 10000;  â†’ sipush 10000 (3 bytes)
  int d = 1000000; â†’ ldc #N (2 bytes, Constant Pool ì‚¬ìš©)

ìµœì í™”:
  javacëŠ” ìƒìˆ˜ê°’ì— ë”°ë¼ ê°€ì¥ ì§§ì€ ëª…ë ¹ì–´ ì„ íƒ
  â†’ í´ë˜ìŠ¤ íŒŒì¼ í¬ê¸° ìµœì†Œí™”
```

---

### 5. Load & Store ëª…ë ¹ì–´

```
Local Variable Array (LVA) â†” Operand Stack

Load (LVA â†’ Stack):
  iload_0, iload_1, iload_2, iload_3  â†’ LVA[0~3]ì˜ int ê°’
  iload <n>                           â†’ LVA[n]ì˜ int ê°’
  
  fload_0, fload_1, ...
  aload_0, aload_1, ...  (a = reference)
  lload_0, lload_1, ...  (longì€ 2ìŠ¬ë¡¯ ì°¨ì§€)

Store (Stack â†’ LVA):
  istore_0, istore_1, istore_2, istore_3
  istore <n>
  
  fstore_0, fstore_1, ...
  astore_0, astore_1, ...

ì˜ˆ:
  void foo(int a, int b) {
      int c = a + b;
  }
  
  ë°”ì´íŠ¸ì½”ë“œ:
  0: iload_1      // LVA[1](a) â†’ Stack
  1: iload_2      // LVA[2](b) â†’ Stack
  2: iadd         // Stackì—ì„œ ë‘ ê°’ pop, ë”í•œ í›„ push
  3: istore_3     // Stack â†’ LVA[3](c)
```

---

### 6. ì‚°ìˆ  ì—°ì‚° ëª…ë ¹ì–´

```
int ì—°ì‚°:
  iadd, isub, imul, idiv, irem
  ineg (ë¶€í˜¸ ë°˜ì „)
  iand, ior, ixor (ë¹„íŠ¸ ì—°ì‚°)
  ishl, ishr, iushr (ì‹œí”„íŠ¸)

long ì—°ì‚°:
  ladd, lsub, lmul, ldiv, lrem
  lneg
  land, lor, lxor
  lshl, lshr, lushr

float ì—°ì‚°:
  fadd, fsub, fmul, fdiv, frem
  fneg

double ì—°ì‚°:
  dadd, dsub, dmul, ddiv, drem
  dneg

ìŠ¤íƒ ë™ì‘:
  iadd:
    Stack ì „: [a, b]  (bê°€ top)
    Stack í›„: [a+b]
```

---

### 7. íƒ€ì… ë³€í™˜ ëª…ë ¹ì–´

```
Widening (ìë™ í™•ì¥, ì •ë³´ ì†ì‹¤ ì—†ìŒ):
  i2l  â†’ int to long
  i2f  â†’ int to float
  i2d  â†’ int to double
  l2f  â†’ long to float
  l2d  â†’ long to double
  f2d  â†’ float to double

Narrowing (ì¶•ì†Œ, ì •ë³´ ì†ì‹¤ ê°€ëŠ¥):
  l2i  â†’ long to int
  f2i  â†’ float to int
  d2i  â†’ double to int
  d2l  â†’ double to long
  d2f  â†’ double to float
  i2b  â†’ int to byte
  i2c  â†’ int to char
  i2s  â†’ int to short

ì˜ˆ:
  long l = 10;
  int i = (int) l;
  
  ë°”ì´íŠ¸ì½”ë“œ:
  ldc2_w 10   // long 10ì„ ìŠ¤íƒì—
  l2i         // long â†’ int ë³€í™˜
  istore_1    // iì— ì €ì¥
```

---

### 8. ì œì–´ íë¦„ ëª…ë ¹ì–´

```
ì¡°ê±´ ë¶„ê¸° (if):
  ifeq  â†’ 0ì´ë©´ ì í”„
  ifne  â†’ 0ì´ ì•„ë‹ˆë©´ ì í”„
  iflt  â†’ < 0 ì´ë©´ ì í”„
  ifle  â†’ <= 0 ì´ë©´ ì í”„
  ifgt  â†’ > 0 ì´ë©´ ì í”„
  ifge  â†’ >= 0 ì´ë©´ ì í”„

ë¹„êµ í›„ ë¶„ê¸° (if_cmp):
  if_icmpeq  â†’ ë‘ int ê°’ì´ ê°™ìœ¼ë©´ ì í”„
  if_icmpne  â†’ ë‘ int ê°’ì´ ë‹¤ë¥´ë©´ ì í”„
  if_icmplt  â†’ v1 < v2 ì´ë©´ ì í”„
  if_icmple  â†’ v1 <= v2 ì´ë©´ ì í”„
  if_icmpgt  â†’ v1 > v2 ì´ë©´ ì í”„
  if_icmpge  â†’ v1 >= v2 ì´ë©´ ì í”„

ë¬´ì¡°ê±´ ì í”„:
  goto <offset>

ì˜ˆ:
  if (a > b) {
      ...
  }
  
  ë°”ì´íŠ¸ì½”ë“œ:
  0: iload_1        // a
  1: iload_2        // b
  2: if_icmple 8    // a <= b ì´ë©´ 8ë²ˆìœ¼ë¡œ ì í”„
  5: ...            // a > bì¼ ë•Œ ì‹¤í–‰
  8: ...            // ë‹¤ìŒ ì½”ë“œ
```

---

## ğŸ’» ì‹¤í—˜ìœ¼ë¡œ í™•ì¸í•˜ê¸°

### ì‹¤í—˜ 1: javapë¡œ ë°”ì´íŠ¸ì½”ë“œ í™•ì¸

```java
public class BytecodeDemo {
    public int add(int a, int b) {
        return a + b;
    }
    
    public int multiply(int x, int y) {
        int result = x * y;
        return result;
    }
}
```

```bash
javac BytecodeDemo.java
javap -c BytecodeDemo.class

# ì¶œë ¥:
# public int add(int, int);
#   Code:
#      0: iload_1       // a
#      1: iload_2       // b
#      2: iadd          // a + b
#      3: ireturn       // ë°˜í™˜

# public int multiply(int, int);
#   Code:
#      0: iload_1       // x
#      1: iload_2       // y
#      2: imul          // x * y
#      3: istore_3      // resultì— ì €ì¥
#      4: iload_3       // result
#      5: ireturn       // ë°˜í™˜
```

---

### ì‹¤í—˜ 2: ìƒìˆ˜ ë¡œë“œ ìµœì í™” ê´€ì°°

```java
public class ConstantDemo {
    public void constants() {
        int a = 0;
        int b = 5;
        int c = 100;
        int d = 10000;
        int e = 1000000;
    }
}
```

```bash
javap -c ConstantDemo.class

# ì¶œë ¥:
# public void constants();
#   Code:
#      0: iconst_0         // a = 0 (1 byte)
#      1: istore_1
#      2: iconst_5         // b = 5 (1 byte)
#      3: istore_2
#      4: bipush 100       // c = 100 (2 bytes)
#      6: istore_3
#      7: sipush 10000     // d = 10000 (3 bytes)
#     10: istore 4
#     12: ldc #2           // e = 1000000 (2 bytes + Constant Pool)
#     14: istore 5
```

---

### ì‹¤í—˜ 3: ì œì–´ íë¦„ ë°”ì´íŠ¸ì½”ë“œ

```java
public class ControlFlow {
    public int max(int a, int b) {
        if (a > b) {
            return a;
        } else {
            return b;
        }
    }
}
```

```bash
javap -c ControlFlow.class

# ì¶œë ¥:
# public int max(int, int);
#   Code:
#      0: iload_1         // a
#      1: iload_2         // b
#      2: if_icmple 7     // a <= b ì´ë©´ 7ë²ˆìœ¼ë¡œ ì í”„
#      5: iload_1         // a
#      6: ireturn         // return a
#      7: iload_2         // b (else ë¸”ë¡)
#      8: ireturn         // return b
```

---

### ì‹¤í—˜ 4: ë°”ì´ë„ˆë¦¬ opcode í™•ì¸

```bash
hexdump -C BytecodeDemo.class | grep -A5 "Code:"

# add ë©”ì„œë“œ ë°”ì´íŠ¸ì½”ë“œ:
# 1B 1C 60 AC
# ^^iload_1  ^^iload_2  ^^iadd  ^^ireturn

# Opcode ë§¤í•‘:
# 0x1B = iload_1 (27)
# 0x1C = iload_2 (28)
# 0x60 = iadd (96)
# 0xAC = ireturn (172)
```

---

## âš¡ ì‹¤ë¬´ ì„íŒ©íŠ¸

### JIT ì»´íŒŒì¼ëŸ¬ì™€ ë°”ì´íŠ¸ì½”ë“œ

```
ë°”ì´íŠ¸ì½”ë“œëŠ” JIT ì»´íŒŒì¼ëŸ¬ì˜ ì…ë ¥:

Interpreter ëª¨ë“œ (Warm-up):
  ë°”ì´íŠ¸ì½”ë“œë¥¼ í•˜ë‚˜ì”© í•´ì„ ì‹¤í–‰
  ëŠë¦¬ì§€ë§Œ ì¦‰ì‹œ ì‹œì‘ ê°€ëŠ¥

JIT ì»´íŒŒì¼ (Hot Method):
  ë°”ì´íŠ¸ì½”ë“œ â†’ ë„¤ì´í‹°ë¸Œ ê¸°ê³„ì–´
  ë¹ ë¥´ì§€ë§Œ ì»´íŒŒì¼ ë¹„ìš© ë°œìƒ
  
C1 (Client Compiler):
  ë¹ ë¥¸ ì»´íŒŒì¼, ê¸°ë³¸ ìµœì í™”
  iadd â†’ add eax, ebx
  
C2 (Server Compiler):
  ëŠë¦° ì»´íŒŒì¼, ê³ ê¸‰ ìµœì í™”
  - Inlining
  - Escape Analysis
  - Loop Unrolling
  
ë°”ì´íŠ¸ì½”ë“œê°€ ê°„ê²°í• ìˆ˜ë¡:
  - íŒŒì‹± ë¹ ë¦„
  - JIT ì»´íŒŒì¼ ë¹ ë¦„
  - ìµœì í™” ê¸°íšŒ ë§ìŒ
```

### ë°”ì´íŠ¸ì½”ë“œ í¬ê¸°ì™€ ë©”ì„œë“œ ì¸ë¼ì´ë‹

```
JIT ì¸ë¼ì´ë‹ ì„ê³„ê°’:
  -XX:MaxInlineSize=35 (ê¸°ë³¸)
  â†’ ë°”ì´íŠ¸ì½”ë“œ 35ë°”ì´íŠ¸ ì´í•˜ ë©”ì„œë“œë§Œ ì¸ë¼ì¸

ì‘ì€ ë©”ì„œë“œ ì˜ˆ:
  public int getX() { return x; }
  â†’ ë°”ì´íŠ¸ì½”ë“œ: aload_0, getfield, ireturn (6 bytes)
  â†’ ì¸ë¼ì¸ ê°€ëŠ¥

í° ë©”ì„œë“œ:
  ë³µì¡í•œ ë¡œì§ (100+ bytes)
  â†’ ì¸ë¼ì¸ ë¶ˆê°€
  â†’ ë©”ì„œë“œ í˜¸ì¶œ ì˜¤ë²„í—¤ë“œ ë°œìƒ

ìµœì í™” íŒ:
  ìì£¼ í˜¸ì¶œë˜ëŠ” ë©”ì„œë“œëŠ” ì‘ê²Œ ìœ ì§€
  â†’ ì¸ë¼ì¸ ê°€ëŠ¥ â†’ ì„±ëŠ¥ í–¥ìƒ
```

### ë°”ì´íŠ¸ì½”ë“œ ê²€ì¦ê³¼ ë³´ì•ˆ

```
Bytecode Verifier:
  í´ë˜ìŠ¤ ë¡œë”© ì‹œ ë°”ì´íŠ¸ì½”ë“œ ê²€ì¦
  
ê²€ì¦ í•­ëª©:
  1. ìŠ¤íƒ ì˜¤ë²„í”Œë¡œìš°/ì–¸ë”í”Œë¡œìš°
     max_stack ë²”ìœ„ ë‚´ ì—°ì‚°
     
  2. íƒ€ì… ì•ˆì „ì„±
     iload í›„ iadd (OK)
     iload í›„ fadd (NG â†’ VerifyError)
     
  3. ì ‘ê·¼ ì œì–´
     private ë©”ì„œë“œë¥¼ ì™¸ë¶€ì—ì„œ í˜¸ì¶œ (NG)
     
  4. Control Flow
     ëª¨ë“  ê²½ë¡œì—ì„œ return
     gotoê°€ ë©”ì„œë“œ ë°–ìœ¼ë¡œ ì í”„ ì•ˆ í•¨

ì•…ì˜ì  ë°”ì´íŠ¸ì½”ë“œ ì°¨ë‹¨:
  ìˆ˜ë™ ì¡°ì‘ëœ .class íŒŒì¼
  â†’ Verifierê°€ ê±°ë¶€
  â†’ ClassFormatError / VerifyError
```

---

## ğŸš« í”í•œ ì˜¤í•´

### "ë°”ì´íŠ¸ì½”ë“œ ëª…ë ¹ì–´ëŠ” 256ê°œë‹¤"

```
âŒ ì˜ëª»ëœ ì´í•´:
  opcodeê°€ 1 byteì´ë¯€ë¡œ ëª…ë ¹ì–´ê°€ 256ê°œë‹¤.

âœ… ì‹¤ì œ:
  ì •ì˜ëœ ëª…ë ¹ì–´: ì•½ 200ê°œ
  ì˜ˆì•½ë¨: 0xBA (breakpoint), 0xFE, 0xFF (ë‚´ë¶€ ì‚¬ìš©)
  ë¯¸ì‚¬ìš©: 56ê°œ ì •ë„
  
  ì´ìœ :
  - íƒ€ì…ë³„ ë¶„ë¦¬ë¡œ ëª…ë ¹ì–´ ìˆ˜ ì¦ê°€
  - í•˜ì§€ë§Œ ëª¨ë“  ì¡°í•©ì´ í•„ìš”í•œ ê±´ ì•„ë‹˜
  - ì˜ˆ: lload_4, lload_5 ê°™ì€ ê±´ ì—†ìŒ (lload <n> ì‚¬ìš©)
```

### "iload_0ì€ í•­ìƒ thisë¥¼ ë¡œë“œí•œë‹¤"

```
âŒ ì˜ëª»ëœ ì´í•´:
  iload_0ì€ thisë¥¼ ì˜ë¯¸í•œë‹¤.

âœ… ì‹¤ì œ:
  iload_0 â†’ LVA[0]ì˜ int ê°’
  aload_0 â†’ LVA[0]ì˜ reference ê°’
  
  ì¸ìŠ¤í„´ìŠ¤ ë©”ì„œë“œ:
  LVA[0] = this (aload_0ìœ¼ë¡œ ì ‘ê·¼)
  LVA[1~] = ë§¤ê°œë³€ìˆ˜ + ì§€ì—­ ë³€ìˆ˜
  
  static ë©”ì„œë“œ:
  LVA[0] = ì²« ë²ˆì§¸ ë§¤ê°œë³€ìˆ˜
  (this ì—†ìŒ)

ì˜ˆ:
  void foo(int x) {  // ì¸ìŠ¤í„´ìŠ¤ ë©”ì„œë“œ
      int y = x + 1;
  }
  // LVA[0]=this, LVA[1]=x, LVA[2]=y
  // x ì ‘ê·¼: iload_1 (not iload_0)
```

### "ëª¨ë“  íƒ€ì…ì— _0, _1, _2, _3 ë²„ì „ì´ ìˆë‹¤"

```
âŒ ì˜ëª»ëœ ì´í•´:
  lload_0, lload_1, lload_2, lload_3ì´ ëª¨ë‘ ì¡´ì¬í•œë‹¤.

âœ… ì‹¤ì œ:
  long, doubleì€ 2ìŠ¬ë¡¯ ì°¨ì§€
  â†’ lload_0, lload_1, lload_2, lload_3 ì¡´ì¬
  â†’ lload_4, lload_5ëŠ” ì—†ìŒ (lload <n> ì‚¬ìš©)
  
  int, float, reference:
  iload_0~3, fload_0~3, aload_0~3
  istore_0~3, fstore_0~3, astore_0~3
  
  ì´ìœ :
  LVA[0~3]ì´ ê°€ì¥ ë¹ˆë²ˆí•˜ê²Œ ì‚¬ìš©
  â†’ ì „ìš© ëª…ë ¹ì–´ë¡œ 1ë°”ì´íŠ¸ ì ˆì•½
```

---

## ğŸ“Œ í•µì‹¬ ì •ë¦¬

```
ë°”ì´íŠ¸ì½”ë“œ ê¸°ë³¸
  Opcode (1 byte) + Operands
  ì•½ 200ê°œ ëª…ë ¹ì–´
  íƒ€ì…ë³„ ë¶„ë¦¬ (i, l, f, d, a)

ëª…ë ¹ì–´ ì¹´í…Œê³ ë¦¬
  Load/Store: LVA â†” Stack
  Arithmetic: add, sub, mul, div
  Control Flow: if, goto
  Method Call: invoke*
  Object: new, getfield, putfield

íƒ€ì…ë³„ ëª…ë ¹ì–´ ë¶„ë¦¬
  iload, fload, aload (íƒ€ì… ì•ˆì „ì„±)
  Bytecode Verifierê°€ íƒ€ì… ê²€ì¦
  JIT ìµœì í™” íŒíŠ¸

ìƒìˆ˜ ë¡œë“œ ìµœì í™”
  iconst_0~5 (1 byte)
  bipush -128~127 (2 bytes)
  sipush -32768~32767 (3 bytes)
  ldc (Constant Pool)

Load/Store
  iload_0~3: LVA[0~3] â†’ Stack
  istore_0~3: Stack â†’ LVA[0~3]
  long/doubleì€ 2ìŠ¬ë¡¯

ì œì–´ íë¦„
  if_icmpeq, if_icmplt, ... (ë¹„êµ í›„ ë¶„ê¸°)
  ifeq, ifne, iflt, ... (0ê³¼ ë¹„êµ í›„ ë¶„ê¸°)
  goto (ë¬´ì¡°ê±´ ì í”„)

ì‹¤ë¬´ ì„íŒ©íŠ¸
  ë°”ì´íŠ¸ì½”ë“œ í¬ê¸° < 35 bytes â†’ JIT ì¸ë¼ì¸ ê°€ëŠ¥
  Bytecode Verifierê°€ íƒ€ì…/ë³´ì•ˆ ê²€ì¦
  JIT ì»´íŒŒì¼ëŸ¬ì˜ ìµœì í™” ì…ë ¥
```

---

## ğŸ¤” ìƒê°í•´ë³¼ ë¬¸ì œ

**Q1.** ë‹¤ìŒ Java ì½”ë“œì˜ ë°”ì´íŠ¸ì½”ë“œë¥¼ ì‘ì„±í•˜ë¼. ê° ëª…ë ¹ì–´ê°€ ìŠ¤íƒì— ë¯¸ì¹˜ëŠ” ì˜í–¥ì„ ì„¤ëª…í•˜ë¼.

```java
int calculate(int x) {
    int y = x * 2;
    return y + 1;
}
```

**Q2.** `int a = 127;`ê³¼ `int b = 128;`ì˜ ë°”ì´íŠ¸ì½”ë“œê°€ ì™œ ë‹¤ë¥¸ê°€? ì–´ë–¤ ëª…ë ¹ì–´ë¥¼ ì‚¬ìš©í•˜ë©° í´ë˜ìŠ¤ íŒŒì¼ í¬ê¸°ì— ì–´ë–¤ ì˜í–¥ì„ ì£¼ëŠ”ê°€?

**Q3.** ë‹¤ìŒ ë‘ ë©”ì„œë“œ ì¤‘ JIT ì¸ë¼ì´ë‹ì— ë” ìœ ë¦¬í•œ ê²ƒì€? ë°”ì´íŠ¸ì½”ë“œ í¬ê¸°ì™€ ì—°ê²°í•´ ì„¤ëª…í•˜ë¼.

```java
// ë°©ë²• 1
int getArea() {
    return width * height;
}

// ë°©ë²• 2
int getArea() {
    int w = getWidth();
    int h = getHeight();
    return w * h;
}
```

> ğŸ’¡ **í•´ì„¤**
>
> **Q1.** ë°”ì´íŠ¸ì½”ë“œ: `0: iload_1` (LVA[1]=x â†’ Stack), `1: iconst_2` (2 â†’ Stack), `2: imul` (Stackì—ì„œ x, 2 pop â†’ x*2 push), `3: istore_2` (Stack â†’ LVA[2]=y), `4: iload_2` (y â†’ Stack), `5: iconst_1` (1 â†’ Stack), `6: iadd` (y, 1 pop â†’ y+1 push), `7: ireturn` (Stack top ë°˜í™˜). ìŠ¤íƒ ë³€í™”: [] â†’ [x] â†’ [x,2] â†’ [x*2] â†’ [] â†’ [y] â†’ [y,1] â†’ [y+1] â†’ [].
>
> **Q2.** `int a = 127;` â†’ `bipush 127` (2 bytes: opcode 0x10 + operand 0x7F). `int b = 128;` â†’ `sipush 128` (3 bytes: opcode 0x11 + operand 0x00 0x80). ì´ìœ : `bipush`ëŠ” -128~127ë§Œ ì§€ì› (1 byte signed). 128ì€ ë²”ìœ„ ë°–ì´ë¼ `sipush` ì‚¬ìš© (2 bytes signed). í´ë˜ìŠ¤ íŒŒì¼ í¬ê¸° 1ë°”ì´íŠ¸ ì¦ê°€. ìˆ˜ë°± ê°œ ìƒìˆ˜ê°€ ìˆë‹¤ë©´ ëˆ„ì  ì˜í–¥ ì»¤ì§.
>
> **Q3.** ë°©ë²• 1ì´ ìœ ë¦¬. ì´ìœ : ë°©ë²• 1 ë°”ì´íŠ¸ì½”ë“œ ~10 bytes (`aload_0`, `getfield width`, `getfield height`, `imul`, `ireturn`). ë°©ë²• 2ëŠ” `getWidth()`, `getHeight()` í˜¸ì¶œ ì¶”ê°€ë¡œ ~20 bytes ì´ìƒ. JIT ì¸ë¼ì´ë‹ ì„ê³„ê°’ 35 bytes ê¸°ì¤€ìœ¼ë¡œ ë°©ë²• 1ì€ ì—¬ìœ  ìˆê³ , ë°©ë²• 2ëŠ” ë©”ì„œë“œ í¬ê¸°ê°€ ì»¤ì ¸ ì¸ë¼ì¸ ê°€ëŠ¥ì„± ë‚®ì•„ì§. ë˜í•œ ë°©ë²• 1ì€ ë©”ì„œë“œ í˜¸ì¶œ ì˜¤ë²„í—¤ë“œ ì—†ìŒ. ë‹¨, `getWidth()`/`getHeight()`ë„ ì‘ìœ¼ë©´ ì¬ê·€ ì¸ë¼ì¸ ê°€ëŠ¥í•˜ì§€ë§Œ ë³´ì¥ ì•ˆ ë¨.

---

## ğŸ“š ì°¸ê³  ìë£Œ

- [JVMS Chapter 6 â€” The Java Virtual Machine Instruction Set](https://docs.oracle.com/javase/specs/jvms/se21/html/jvms-6.html)
- [JVM Opcodes Reference](https://en.wikipedia.org/wiki/Java_bytecode_instruction_listings)
- [OpenJDK Bytecode Interpreter](https://github.com/openjdk/jdk/tree/master/src/hotspot/share/interpreter)

---

<div align="center">

**[â¬…ï¸ ì´ì „: Class File Format](./01-class-file-format.md)** | **[ë‹¤ìŒ: Operand Stack Mechanism â¡ï¸](./03-operand-stack-mechanism.md)**

</div>
