# Exception Handling Bytecode - ì˜ˆì™¸ ì²˜ë¦¬ ë°”ì´íŠ¸ì½”ë“œ

---

## ğŸ¯ í•µì‹¬ ì§ˆë¬¸

ì´ ë¬¸ì„œë¥¼ ì½ê³  ë‚˜ë©´ ë‹¤ìŒ ì§ˆë¬¸ì— ë‹µí•  ìˆ˜ ìˆìŠµë‹ˆë‹¤.

- `try-catch-finally`ëŠ” ë°”ì´íŠ¸ì½”ë“œë¡œ ì–´ë–»ê²Œ ë³€í™˜ë˜ëŠ”ê°€?
- Exception Tableì€ ë¬´ì—‡ì´ë©°, JVMì€ ì–´ë–»ê²Œ ì˜ˆì™¸ë¥¼ catchí•˜ëŠ”ê°€?
- `athrow` ëª…ë ¹ì–´ëŠ” ì–´ë–»ê²Œ ë™ì‘í•˜ë©°, ìŠ¤íƒ ìƒíƒœëŠ” ì–´ë–»ê²Œ ë³€í•˜ëŠ”ê°€?
- `finally` ë¸”ë¡ì€ ì™œ ë°”ì´íŠ¸ì½”ë“œì—ì„œ ì¤‘ë³µë˜ì–´ ë‚˜íƒ€ë‚˜ëŠ”ê°€?
- `try-with-resources`ëŠ” ë°”ì´íŠ¸ì½”ë“œì—ì„œ ì–´ë–»ê²Œ êµ¬í˜„ë˜ëŠ”ê°€?

---

## ğŸ” ì™œ ì´ê²Œ ì¡´ì¬í•˜ëŠ”ê°€

### ë¬¸ì œ: ì˜ˆì™¸ ì²˜ë¦¬ë¥¼ ì–´ë–»ê²Œ êµ¬ì¡°í™”í•  ê²ƒì¸ê°€

```java
void readFile() {
    try {
        FileReader fr = new FileReader("file.txt");
        // ...
    } catch (IOException e) {
        e.printStackTrace();
    } finally {
        // cleanup
    }
}
```

```
ì „í†µì  C ë°©ì‹ (goto):
  FILE* f = fopen("file.txt", "r");
  if (f == NULL) goto error;
  // ...
  error:
    // error handling
  cleanup:
    // cleanup code

ë¬¸ì œ:
  - gotoëŠ” ìŠ¤íŒŒê²Œí‹° ì½”ë“œ ìœ ë°œ
  - ì—ëŸ¬ ì²˜ë¦¬ ëˆ„ë½ ì‰¬ì›€
  - êµ¬ì¡°í™” ì–´ë ¤ì›€

JVM ë°©ì‹ (Exception Table):
  try ë¸”ë¡ ë²”ìœ„ ê¸°ë¡
  ì˜ˆì™¸ ë°œìƒ ì‹œ Table íƒìƒ‰
  â†’ êµ¬ì¡°ì , ëª…í™•
```

ë°”ì´íŠ¸ì½”ë“œëŠ” **Exception Table**ë¡œ ì˜ˆì™¸ë¥¼ ì²˜ë¦¬í•œë‹¤.

---

## ğŸ“ ë‚´ë¶€ êµ¬ì¡°

### 1. Exception Table êµ¬ì¡°

```
Code ì†ì„± ë‚´ Exception Table:

exception_table_length: 2
exception_table:
  start_pc  end_pc  handler_pc  catch_type
  0         10      13          #5 (IOException)
  0         10      20          #0 (any)

ì˜ë¯¸:
  start_pc ~ end_pc: try ë¸”ë¡ ë²”ìœ„ (ë°”ì´íŠ¸ì½”ë“œ ì˜¤í”„ì…‹)
  handler_pc: catch ë¸”ë¡ ì‹œì‘ ìœ„ì¹˜
  catch_type: ì¡ì„ ì˜ˆì™¸ íƒ€ì… (Constant Pool ì¸ë±ìŠ¤)
                #0ì´ë©´ ëª¨ë“  ì˜ˆì™¸ (finally êµ¬í˜„ìš©)

ì˜ˆì™¸ ë°œìƒ ì‹œ JVM ë™ì‘:
  1. í˜„ì¬ PC(Program Counter)ê°€ ì–´ëŠ ë²”ìœ„ì— ìˆëŠ”ì§€ í™•ì¸
  2. Exception Tableì—ì„œ ë§¤ì¹­ë˜ëŠ” ì—”íŠ¸ë¦¬ íƒìƒ‰
  3. ì˜ˆì™¸ íƒ€ì… í™•ì¸ (instanceof)
  4. handler_pcë¡œ ì í”„
  5. ì˜ˆì™¸ ê°ì²´ë¥¼ Operand Stackì— push
```

---

### 2. try-catch ë°”ì´íŠ¸ì½”ë“œ

```java
void example() {
    try {
        riskyMethod();
    } catch (IOException e) {
        System.out.println("IO Error");
    }
}
```

```
ë°”ì´íŠ¸ì½”ë“œ:

   0: aload_0
   1: invokevirtual #2    // riskyMethod
   4: goto 15              // try ë¸”ë¡ ë, catch ê±´ë„ˆë›°ê¸°

   // catch ë¸”ë¡ ì‹œì‘
   7: astore_1             // ì˜ˆì™¸ ê°ì²´ë¥¼ LVA[1](e)ì— ì €ì¥
   8: getstatic #3         // System.out
  11: ldc #4               // "IO Error"
  13: invokevirtual #5    // println
  14: return

  15: return               // ì •ìƒ ì¢…ë£Œ

Exception Table:
  start_pc  end_pc  handler_pc  catch_type
  0         4       7           #6 (IOException)

íë¦„:
  ì •ìƒ: 0 â†’ 1 â†’ 4 (goto 15) â†’ 15 (return)
  ì˜ˆì™¸: 0 â†’ 1 (ì˜ˆì™¸ ë°œìƒ) â†’ Table íƒìƒ‰ â†’ 7 (catch) â†’ ... â†’ 14 (return)
```

---

### 3. try-catch-finally ë°”ì´íŠ¸ì½”ë“œ

```java
void example() {
    try {
        riskyMethod();
    } catch (IOException e) {
        handleError(e);
    } finally {
        cleanup();
    }
}
```

```
ë°”ì´íŠ¸ì½”ë“œ (finally ì¤‘ë³µ):

   // try ë¸”ë¡
   0: aload_0
   1: invokevirtual #2    // riskyMethod
   4: aload_0
   5: invokevirtual #3    // cleanup (finally - ì •ìƒ ê²½ë¡œ)
   8: goto 30

   // catch ë¸”ë¡
  11: astore_1             // IOException e
  12: aload_0
  13: aload_1
  14: invokevirtual #4    // handleError(e)
  17: aload_0
  18: invokevirtual #3    // cleanup (finally - catch ê²½ë¡œ)
  21: goto 30

   // finally ë¸”ë¡ (ì˜ˆì™¸ ì¬throwìš©)
  24: astore_2             // any exception
  25: aload_0
  26: invokevirtual #3    // cleanup (finally - ì¬throw ê²½ë¡œ)
  29: aload_2
  30: athrow               // ì˜ˆì™¸ ì¬throw

  33: return

Exception Table:
  start_pc  end_pc  handler_pc  catch_type
  0         4       11          #5 (IOException)
  0         4       24          #0 (any - finally)
  11        17      24          #0 (any - finally)

íŠ¹ì§•:
  cleanup() í˜¸ì¶œì´ 3ë²ˆ ì¤‘ë³µë¨
  â†’ ì •ìƒ, catch, ì¬throw ê²½ë¡œ ê°ê°
  â†’ ë°”ì´íŠ¸ì½”ë“œ í¬ê¸° ì¦ê°€
```

---

### 4. athrow ëª…ë ¹ì–´

```
athrow (Throw Exception):

ë™ì‘:
  1. Operand Stackì—ì„œ ì˜ˆì™¸ ê°ì²´ pop
  2. í˜„ì¬ ë©”ì„œë“œì˜ Exception Table íƒìƒ‰
  3. ë§¤ì¹­ë˜ëŠ” handler ì—†ìœ¼ë©´ ë©”ì„œë“œ ì¢…ë£Œ
  4. callerì˜ Exception Table íƒìƒ‰
  5. ìµœì¢…ì ìœ¼ë¡œ ì²˜ë¦¬ ì•ˆ ë˜ë©´ ìŠ¤ë ˆë“œ ì¢…ë£Œ

ìŠ¤íƒ ë³€í™”:
  throw ì „: [..., exception_obj]
  athrow ì‹¤í–‰
  â†’ í˜„ì¬ ìŠ¤íƒ í´ë¦¬ì–´
  â†’ handler_pcë¡œ ì í”„
  â†’ ìƒˆ ìŠ¤íƒ: [exception_obj]

ë°”ì´íŠ¸ì½”ë“œ:
  new #2              // new IOException
  dup
  ldc #3              // "Error message"
  invokespecial #4   // IOException.<init>(String)
  athrow              // throw
```

---

### 5. try-with-resources ë°”ì´íŠ¸ì½”ë“œ

```java
void example() {
    try (FileReader fr = new FileReader("file.txt")) {
        // use fr
    }
}
```

```
ë°”ì´íŠ¸ì½”ë“œ (ë§¤ìš° ë³µì¡):

   0: new #2              // FileReader
   3: dup
   4: ldc #3              // "file.txt"
   6: invokespecial #4   // FileReader.<init>
   9: astore_1            // fr ì €ì¥

  10: aload_1
  11: invokevirtual #5   // use fr (ìƒëµ)

  // ì •ìƒ ì¢…ë£Œ ì‹œ close
  14: aload_1
  15: ifnull 43
  18: aload_1
  19: invokevirtual #6   // fr.close()
  22: goto 43

  // try ë¸”ë¡ì—ì„œ ì˜ˆì™¸ ë°œìƒ
  25: astore_2            // ì˜ˆì™¸ ì €ì¥
  26: aload_1
  27: ifnull 40
  30: aload_1
  31: invokevirtual #6   // fr.close()
  34: goto 40
  37: invokevirtual #7   // addSuppressed (close ì‹¤íŒ¨ ì‹œ)
  40: aload_2
  41: athrow              // ì›ë˜ ì˜ˆì™¸ ì¬throw

  // close()ì—ì„œ ì˜ˆì™¸ ë°œìƒ
  42: ...

Exception Table:
  start_pc  end_pc  handler_pc  catch_type
  10        14      25          #0 (any)
  30        34      37          #8 (Throwable - addSuppressedìš©)
  ...

íŠ¹ì§•:
  - close() í˜¸ì¶œì´ ì—¬ëŸ¬ ë²ˆ ì¤‘ë³µ
  - close() ì‹¤íŒ¨ ì‹œ addSuppressed() ì²˜ë¦¬
  - ì›ë³¸ ì˜ˆì™¸ ìš°ì„ , close ì˜ˆì™¸ëŠ” suppressed
  â†’ ë°”ì´íŠ¸ì½”ë“œ ë§¤ìš° ë³µì¡ (ìˆ˜ì‹­ ì¤„)
```

---

## ğŸ’» ì‹¤í—˜ìœ¼ë¡œ í™•ì¸í•˜ê¸°

### ì‹¤í—˜ 1: Exception Table í™•ì¸

```java
public class ExceptionDemo {
    public void simple() {
        try {
            riskyMethod();
        } catch (IOException e) {
            e.printStackTrace();
        } catch (Exception e) {
            System.out.println("General error");
        }
    }
    
    void riskyMethod() throws IOException { }
}
```

```bash
javap -c -v ExceptionDemo.class

# simple ë©”ì„œë“œ:
# Exception table:
#    from    to  target type
#        0     4     7   Class java/io/IOException
#        0     4    17   Class java/lang/Exception
#
# Code:
#    0: aload_0
#    1: invokevirtual #2   // riskyMethod
#    4: goto 27
#    7: astore_1            // IOException
#    8: aload_1
#    9: invokevirtual #4   // printStackTrace
#   12: goto 27
#   17: astore_1            // Exception
#   18: getstatic #5        // System.out
#   21: ldc #6              // "General error"
#   23: invokevirtual #7   // println
#   26: return
#   27: return
```

---

### ì‹¤í—˜ 2: finally ë¸”ë¡ ì¤‘ë³µ í™•ì¸

```java
public class FinallyDemo {
    public void test() {
        try {
            System.out.println("try");
        } finally {
            System.out.println("finally");
        }
    }
}
```

```bash
javap -c FinallyDemo.class

# Code:
#    0: getstatic #2    // System.out
#    3: ldc #3          // "try"
#    5: invokevirtual #4
#    8: getstatic #2    // System.out (finally - ì •ìƒ ê²½ë¡œ)
#   11: ldc #5          // "finally"
#   13: invokevirtual #4
#   16: goto 30
#   19: astore_1        // any exception
#   20: getstatic #2    // System.out (finally - ì˜ˆì™¸ ê²½ë¡œ)
#   23: ldc #5          // "finally"
#   25: invokevirtual #4
#   28: aload_1
#   29: athrow
#   30: return

# "finally" ë¬¸ìì—´ê³¼ println í˜¸ì¶œì´ 2ë²ˆ ë°˜ë³µë¨
```

---

### ì‹¤í—˜ 3: try-with-resources ë³µì¡ë„

```java
public class TryWithResourcesDemo {
    public void simple() {
        try (FileReader fr = new FileReader("test.txt")) {
            int c = fr.read();
        } catch (IOException e) {
            e.printStackTrace();
        }
    }
}
```

```bash
javap -c TryWithResourcesDemo.class

# Code ê¸¸ì´: ~100 lines
# Exception Table: 5~7ê°œ ì—”íŠ¸ë¦¬
# close() í˜¸ì¶œ: ì—¬ëŸ¬ ê²½ë¡œì—ì„œ ì¤‘ë³µ
# addSuppressed() ì²˜ë¦¬: ë³„ë„ ì˜ˆì™¸ ì²˜ë¦¬ ë¸”ë¡

# â†’ ë‹¨ìˆœí•´ ë³´ì´ì§€ë§Œ ë°”ì´íŠ¸ì½”ë“œëŠ” ë§¤ìš° ë³µì¡
```

---

## âš¡ ì‹¤ë¬´ ì„íŒ©íŠ¸

### try-catch ì„±ëŠ¥ ì˜¤ë²„í—¤ë“œ

```
ì˜ˆì™¸ê°€ ë°œìƒí•˜ì§€ ì•Šì„ ë•Œ:
  try ë¸”ë¡ ì§„ì…: ê±°ì˜ ì˜¤ë²„í—¤ë“œ ì—†ìŒ
  Exception Tableì€ ë©”íƒ€ë°ì´í„°ì¼ ë¿
  â†’ ì„±ëŠ¥ ì˜í–¥ ë¯¸ë¯¸

ì˜ˆì™¸ê°€ ë°œìƒí•  ë•Œ:
  1. Exception Table íƒìƒ‰
  2. Stack Unwinding (ë©”ì„œë“œ ì—­ìˆœ íƒìƒ‰)
  3. ì˜ˆì™¸ ê°ì²´ ìƒì„± (+ Stack Trace)
  â†’ ë§¤ìš° ëŠë¦¼ (ì •ìƒ ì‹¤í–‰ ëŒ€ë¹„ 100~1000ë°°)

ê¶Œì¥:
  ì˜ˆì™¸ëŠ” ì˜ˆì™¸ì ì¸ ê²½ìš°ì—ë§Œ ì‚¬ìš©
  ì •ìƒ íë¦„ ì œì–´ì— ì‚¬ìš© ê¸ˆì§€
  
// âŒ ì•ˆí‹°íŒ¨í„´
try {
    return map.get(key);
} catch (NullPointerException e) {
    return null;
}

// âœ… ì •ìƒ íŒ¨í„´
return map.getOrDefault(key, null);
```

### finally vs try-with-resources

```
finally ë¬¸ì œ:
  - ì½”ë“œ ì¤‘ë³µ (ë°”ì´íŠ¸ì½”ë“œ)
  - close() ëˆ„ë½ ê°€ëŠ¥
  - ë³µì¡í•œ ì˜ˆì™¸ ì²˜ë¦¬ í•„ìš”

try-with-resources ì¥ì :
  - ìë™ close() ë³´ì¥
  - Suppressed Exception ìë™ ì²˜ë¦¬
  - ì½”ë“œ ê°„ê²°

ë°”ì´íŠ¸ì½”ë“œ í¬ê¸°:
  finally: ~30 lines
  try-with-resources: ~100 lines
  â†’ ì»´íŒŒì¼ëŸ¬ê°€ ì•ˆì „í•˜ê²Œ í™•ì¥
  
ê¶Œì¥:
  AutoCloseable êµ¬í˜„ ì‹œ í•­ìƒ try-with-resources ì‚¬ìš©
```

### Exception Tableê³¼ JIT ìµœì í™”

```
JIT ì»´íŒŒì¼ëŸ¬ ê´€ì :

try ë¸”ë¡ì´ ë§ì€ ë©”ì„œë“œ:
  - Exception Tableì´ ë³µì¡
  - ìµœì í™” ë²”ìœ„ ì œí•œ
  - ì¸ë¼ì´ë‹ ì–´ë ¤ì›€

ì„±ëŠ¥ ìµœì í™”:
  - Hot Pathì— try-catch ìµœì†Œí™”
  - ì˜ˆì™¸ë¥¼ ë©”ì„œë“œ ì™¸ë¶€ë¡œ ìœ„ì„
  
// âŒ ë£¨í”„ ë‚´ try
for (int i = 0; i < 1000000; i++) {
    try {
        process(i);
    } catch (Exception e) { }
}

// âœ… try ë°–ìœ¼ë¡œ ì´ë™
try {
    for (int i = 0; i < 1000000; i++) {
        process(i);
    }
} catch (Exception e) { }
```

---

## ğŸš« í”í•œ ì˜¤í•´

### "finallyëŠ” í•­ìƒ ì‹¤í–‰ëœë‹¤"

```java
âŒ ì˜ëª»ëœ ì´í•´:
  finally ë¸”ë¡ì€ ì–´ë–¤ ê²½ìš°ì—ë„ í•­ìƒ ì‹¤í–‰ëœë‹¤.

âœ… ì‹¤ì œ:
  ëŒ€ë¶€ë¶„ ì‹¤í–‰ë˜ì§€ë§Œ ì˜ˆì™¸ ìˆìŒ
  
ì‹¤í–‰ ì•ˆ ë˜ëŠ” ê²½ìš°:
  1. System.exit()
     try { ... } 
     finally { ... }  // ì‹¤í–‰ ì•ˆ ë¨
     System.exit(0);
  
  2. JVM í¬ë˜ì‹œ
     infinite loop, native crash
  
  3. ìŠ¤ë ˆë“œ ê°•ì œ ì¢…ë£Œ
     thread.stop() (deprecated)
  
  4. finally ë¸”ë¡ ë„ë‹¬ ì „ ë¬´í•œ ë£¨í”„
     try {
         while(true) { }
     } finally { }  // ë„ë‹¬ ë¶ˆê°€

ë°”ì´íŠ¸ì½”ë“œ ê´€ì :
  finallyëŠ” "ì •ìƒ/ì˜ˆì™¸ ê²½ë¡œ ê°ê°ì— ë³µì‚¬"
  ê²½ë¡œì— ë„ë‹¬í•˜ì§€ ëª»í•˜ë©´ ì‹¤í–‰ ì•ˆ ë¨
```

### "try-catchëŠ” ì˜ˆì™¸ ë°œìƒ ì—¬ë¶€ì™€ ë¬´ê´€í•˜ê²Œ ëŠë¦¬ë‹¤"

```
âŒ ì˜ëª»ëœ ì´í•´:
  try ë¸”ë¡ì´ ìˆìœ¼ë©´ ë¬´ì¡°ê±´ ì„±ëŠ¥ ì €í•˜ëœë‹¤.

âœ… ì‹¤ì œ:
  ì˜ˆì™¸ ë°œìƒ ì•ˆ í•˜ë©´ ê±°ì˜ ì˜¤ë²„í—¤ë“œ ì—†ìŒ
  
ë²¤ì¹˜ë§ˆí¬:
  // try ì—†ìŒ
  int sum = 0;
  for (int i = 0; i < 1000000; i++) {
      sum += i;
  }
  // ì‹œê°„: 1ms
  
  // try ìˆìŒ (ì˜ˆì™¸ ì•ˆ ë‚¨)
  try {
      int sum = 0;
      for (int i = 0; i < 1000000; i++) {
          sum += i;
      }
  } catch (Exception e) { }
  // ì‹œê°„: 1ms (ë™ì¼)
  
  // ì˜ˆì™¸ ë°œìƒ
  for (int i = 0; i < 1000000; i++) {
      try {
          throw new Exception();
      } catch (Exception e) { }
  }
  // ì‹œê°„: 1000ms (1000ë°° ëŠë¦¼)

ê²°ë¡ :
  try-catch ìì²´ëŠ” ë¹ ë¦„
  ì˜ˆì™¸ ê°ì²´ ìƒì„± + Stack Unwindingì´ ëŠë¦¼
```

### "catch (Exception e)ëŠ” ëª¨ë“  ì˜ˆì™¸ë¥¼ ì¡ëŠ”ë‹¤"

```
âŒ ì˜ëª»ëœ ì´í•´:
  Exceptionì„ ì¡ìœ¼ë©´ ëª¨ë“  ì˜ˆì™¸ë¥¼ ì²˜ë¦¬í•œë‹¤.

âœ… ì‹¤ì œ:
  ErrorëŠ” ì¡ì§€ ëª»í•¨
  
Throwable ê³„ì¸µ:
  Throwable
  â”œâ”€ Error (ì¡ì§€ ë§ì•„ì•¼ í•¨)
  â”‚  â”œâ”€ OutOfMemoryError
  â”‚  â”œâ”€ StackOverflowError
  â”‚  â””â”€ VirtualMachineError
  â””â”€ Exception (ì¡ì•„ë„ ë¨)
     â”œâ”€ RuntimeException
     â””â”€ IOException

catch (Exception e):
  Exceptionê³¼ ê·¸ í•˜ìœ„ë§Œ catch
  ErrorëŠ” í†µê³¼ â†’ JVMì´ ì²˜ë¦¬

catch (Throwable t):
  ëª¨ë“  ì˜ˆì™¸ catch
  â†’ ê¶Œì¥ ì•ˆ í•¨ (Errorë„ ì¡í˜)
  
ë°”ì´íŠ¸ì½”ë“œ:
  Exception Tableì˜ catch_typeì´ íƒ€ì… ê²°ì •
  #0 (any)ëŠ” ëª¨ë“  Throwable
```

---

## ğŸ“Œ í•µì‹¬ ì •ë¦¬

```
Exception Table
  try ë¸”ë¡ ë²”ìœ„: start_pc ~ end_pc
  catch ë¸”ë¡ ìœ„ì¹˜: handler_pc
  ì˜ˆì™¸ íƒ€ì…: catch_type (Constant Pool ì¸ë±ìŠ¤)

ì˜ˆì™¸ ë°œìƒ ì‹œ íë¦„
  1. PCê°€ Exception Table ë²”ìœ„ ë‚´?
  2. ì˜ˆì™¸ íƒ€ì… ë§¤ì¹­? (instanceof)
  3. handler_pcë¡œ ì í”„
  4. ì˜ˆì™¸ ê°ì²´ â†’ Operand Stack

athrow
  ìŠ¤íƒì—ì„œ ì˜ˆì™¸ ê°ì²´ pop
  Exception Table íƒìƒ‰
  ë§¤ì¹­ ì—†ìœ¼ë©´ callerë¡œ ì „íŒŒ
  ìŠ¤íƒ í´ë¦¬ì–´ í›„ handlerë¡œ ì í”„

finally êµ¬í˜„
  ì •ìƒ/ì˜ˆì™¸/ì¬throw ê²½ë¡œì— ê°ê° ì¤‘ë³µ
  ë°”ì´íŠ¸ì½”ë“œ í¬ê¸° ì¦ê°€
  catch_type=#0 (any) ì‚¬ìš©

try-with-resources
  AutoCloseable.close() ìë™ í˜¸ì¶œ
  Suppressed Exception ì²˜ë¦¬
  ë°”ì´íŠ¸ì½”ë“œ ë§¤ìš° ë³µì¡ (~100 lines)

ì„±ëŠ¥
  try ì§„ì…: ì˜¤ë²„í—¤ë“œ ê±°ì˜ ì—†ìŒ
  ì˜ˆì™¸ ë°œìƒ: ë§¤ìš° ëŠë¦¼ (100~1000ë°°)
  â†’ ì˜ˆì™¸ëŠ” ì˜ˆì™¸ì ì¸ ê²½ìš°ì—ë§Œ

ì‹¤ë¬´ íŒ
  Hot Pathì— try-catch ìµœì†Œí™”
  try-with-resources ê¶Œì¥ (finally ëŒ€ì‹ )
  ë£¨í”„ ë°–ìœ¼ë¡œ try ì´ë™
```

---

## ğŸ¤” ìƒê°í•´ë³¼ ë¬¸ì œ

**Q1.** ë‹¤ìŒ ì½”ë“œì˜ Exception Tableì„ ì‘ì„±í•˜ë¼. start_pc, end_pc, handler_pc, catch_typeë¥¼ ëª…ì‹œí•˜ë¼.

```java
void test() {
    try {
        methodA();
        methodB();
    } catch (IOException e) {
        handleIO(e);
    } catch (Exception e) {
        handleGeneral(e);
    } finally {
        cleanup();
    }
}
```

**Q2.** finally ë¸”ë¡ì´ ë°”ì´íŠ¸ì½”ë“œì—ì„œ 3ë²ˆ ì¤‘ë³µë˜ëŠ” ì´ìœ ë¥¼ ì˜ˆì™¸ ë°œìƒ ê²½ë¡œì™€ ì—°ê²°í•´ ì„¤ëª…í•˜ë¼. ì¤‘ë³µì„ ì œê±°í•  ìˆ˜ ìˆëŠ”ê°€?

**Q3.** ë‹¤ìŒ ë‘ ì½”ë“œì˜ ë°”ì´íŠ¸ì½”ë“œ í¬ê¸°ì™€ ì„±ëŠ¥ì„ ë¹„êµí•˜ë¼.

```java
// ë°©ë²• 1
for (int i = 0; i < 1000; i++) {
    try {
        process(i);
    } catch (Exception e) {
        handle(e);
    }
}

// ë°©ë²• 2
try {
    for (int i = 0; i < 1000; i++) {
        process(i);
    }
} catch (Exception e) {
    handle(e);
}
```

> ğŸ’¡ **í•´ì„¤**
>
> **Q1.** Exception Table (ê°œë…ì ):
> ```
> start_pc  end_pc  handler_pc  catch_type
> 0         10      13          IOException
> 0         10      20          Exception
> 0         10      30          any (finally - ì¬throw)
> 13        17      30          any (finally - IOException catch í›„)
> 20        24      30          any (finally - Exception catch í›„)
> ```
> cleanup()ì€ ì •ìƒ ê²½ë¡œ(10ë²ˆ ì´í›„), IOException catch í›„(17ë²ˆ ì´í›„), Exception catch í›„(24ë²ˆ ì´í›„), ì¬throw ê²½ë¡œ(30ë²ˆ)ì—ì„œ ê°ê° í˜¸ì¶œë¨. ì´ 4ë²ˆ ì¤‘ë³µ.
>
> **Q2.** finally ì¤‘ë³µ ì´ìœ : â‘  ì •ìƒ ì¢…ë£Œ ê²½ë¡œ (try ë) â€” cleanup() í˜¸ì¶œ í›„ return. â‘¡ catch ë¸”ë¡ ê²½ë¡œ â€” catch ì²˜ë¦¬ í›„ cleanup() í˜¸ì¶œ. â‘¢ ì²˜ë¦¬ ì•ˆ ëœ ì˜ˆì™¸ ê²½ë¡œ â€” cleanup() í˜¸ì¶œ í›„ athrowë¡œ ì¬throw. JVMì€ gotoë¡œë§Œ ì œì–´ íë¦„ êµ¬í˜„ â†’ finallyë¥¼ ì„œë¸Œë£¨í‹´ìœ¼ë¡œ í˜¸ì¶œ ë¶ˆê°€ (jsr/retëŠ” deprecated) â†’ ê° ê²½ë¡œì— ì½”ë“œ ë³µì‚¬. ì¤‘ë³µ ì œê±° ë¶ˆê°€: ë°”ì´íŠ¸ì½”ë“œëŠ” êµ¬ì¡°ì  ì í”„ë§Œ ì§€ì›, ì„œë¸Œë£¨í‹´ ë©”ì»¤ë‹ˆì¦˜ ì—†ìŒ (Java 6ë¶€í„° jsr/ret ì œê±°).
>
> **Q3.** ë°”ì´íŠ¸ì½”ë“œ í¬ê¸°: ë°©ë²• 1ì€ ë£¨í”„ ë‚´ try-catch â†’ Exception Tableì´ ë£¨í”„ ì•ˆìª½ ë²”ìœ„ë§Œ ì»¤ë²„ â†’ ì‘ìŒ (~20 lines). ë°©ë²• 2ëŠ” ë£¨í”„ ì „ì²´ë¥¼ tryë¡œ ê°ìŒˆ â†’ Exception Tableì´ ì „ì²´ ë£¨í”„ ì»¤ë²„ â†’ í¬ê¸° ë¹„ìŠ· ë˜ëŠ” ì•½ê°„ í¼. ì„±ëŠ¥: ë°©ë²• 1ì€ ì˜ˆì™¸ ë°œìƒ ì•ˆ í•˜ë©´ ë™ì¼í•˜ì§€ë§Œ, ì˜ˆì™¸ ë°œìƒ ì‹œ ë§¤ë²ˆ Exception Table íƒìƒ‰ (ë¯¸ë¯¸). ë°©ë²• 2ê°€ ì•½ê°„ ìœ ë¦¬ (Exception Table íƒìƒ‰ 1íšŒ). ë‹¨, ì˜ˆì™¸ ë°œìƒ ë¹ˆë„ê°€ ë‚®ìœ¼ë©´ ì°¨ì´ ë¬´ì‹œ ê°€ëŠ¥. JIT ìµœì í™”: ë°©ë²• 2ê°€ ìœ ë¦¬ â€” try ë¸”ë¡ì´ í° ë‹¨ìœ„ë¡œ ìˆì–´ ìµœì í™” ë²”ìœ„ ë„“ìŒ. ê¶Œì¥: ë°©ë²• 2 (tryë¥¼ ë£¨í”„ ë°–ìœ¼ë¡œ).

---

## ğŸ“š ì°¸ê³  ìë£Œ

- [JVMS Â§2.10 â€” Exceptions](https://docs.oracle.com/javase/specs/jvms/se21/html/jvms-2.html#jvms-2.10)
- [JVMS Â§3.12 â€” Throwing and Handling Exceptions](https://docs.oracle.com/javase/specs/jvms/se21/html/jvms-3.html#jvms-3.12)
- [JEP 213 â€” Milling Project Coin (try-with-resources)](https://openjdk.org/jeps/213)

---

<div align="center">

**[â¬…ï¸ ì´ì „: Method Invocation Instructions](./04-method-invocation-instructions.md)** | **[ë‹¤ìŒ: Lambda & InvokeDynamic â¡ï¸](./06-lambda-and-invokedynamic.md)**

</div>
