# Lambda & InvokeDynamic - ëŒë‹¤ì™€ ì¸ë³´í¬ë‹¤ì´ë‚˜ë¯¹

---

## ğŸ¯ í•µì‹¬ ì§ˆë¬¸

ì´ ë¬¸ì„œë¥¼ ì½ê³  ë‚˜ë©´ ë‹¤ìŒ ì§ˆë¬¸ì— ë‹µí•  ìˆ˜ ìˆìŠµë‹ˆë‹¤.

- ëŒë‹¤ í‘œí˜„ì‹ì€ ë°”ì´íŠ¸ì½”ë“œë¡œ ì–´ë–»ê²Œ ë³€í™˜ë˜ëŠ”ê°€?
- ì™œ ëŒë‹¤ëŠ” ë‚´ë¶€ í´ë˜ìŠ¤ê°€ ì•„ë‹Œ `invokedynamic`ì„ ì‚¬ìš©í•˜ëŠ”ê°€?
- `LambdaMetafactory`ëŠ” ë¬´ì—‡ì´ë©°, ì–´ë–»ê²Œ ëŒë‹¤ ì¸ìŠ¤í„´ìŠ¤ë¥¼ ìƒì„±í•˜ëŠ”ê°€?
- `invokedynamic`ì˜ Bootstrap MethodëŠ” ì–¸ì œ ì‹¤í–‰ë˜ë©°, CallSiteëŠ” ë¬´ì—‡ì¸ê°€?
- ëŒë‹¤ì˜ ìº¡ì²˜(capture)ëŠ” ë°”ì´íŠ¸ì½”ë“œì—ì„œ ì–´ë–»ê²Œ ì²˜ë¦¬ë˜ëŠ”ê°€?

---

## ğŸ” ì™œ ì´ê²Œ ì¡´ì¬í•˜ëŠ”ê°€

### ë¬¸ì œ: í•¨ìˆ˜í˜• í”„ë¡œê·¸ë˜ë°ì„ ì–´ë–»ê²Œ JVMì—ì„œ êµ¬í˜„í•  ê²ƒì¸ê°€

```java
// Java 7 ì´ì „ (ìµëª… í´ë˜ìŠ¤)
Runnable r = new Runnable() {
    public void run() {
        System.out.println("Hello");
    }
};

// Java 8+ (ëŒë‹¤)
Runnable r = () -> System.out.println("Hello");
```

```
ìµëª… í´ë˜ìŠ¤ ë¬¸ì œ:
  - í´ë˜ìŠ¤ íŒŒì¼ ì¦ê°€ (Outer$1.class, Outer$2.class...)
  - ë©”ëª¨ë¦¬ ì˜¤ë²„í—¤ë“œ (ë§¤ë²ˆ ìƒˆ ê°ì²´ ìƒì„±)
  - ë°”ì´íŠ¸ì½”ë“œ ê³ ì • (ìµœì í™” ì—¬ì§€ ì—†ìŒ)

ëŒë‹¤ ìš”êµ¬ì‚¬í•­:
  - ê°„ê²°í•œ ë¬¸ë²•
  - íš¨ìœ¨ì ì¸ ë©”ëª¨ë¦¬ ì‚¬ìš©
  - ë¯¸ë˜ ìµœì í™” ê°€ëŠ¥ì„± í™•ë³´
```

JVMì€ ì´ë¥¼ **invokedynamic**ìœ¼ë¡œ í•´ê²°í–ˆë‹¤.

---

## ğŸ“ ë‚´ë¶€ êµ¬ì¡°

### 1. ëŒë‹¤ì˜ ë°”ì´íŠ¸ì½”ë“œ ë³€í™˜

```java
public class LambdaDemo {
    public void test() {
        Runnable r = () -> System.out.println("Hello");
        r.run();
    }
}
```

```bash
javap -c -v LambdaDemo.class

# test ë©”ì„œë“œ:
#    0: invokedynamic #2, 0  // InvokeDynamic #0:run:()Ljava/lang/Runnable;
#    5: astore_1
#    6: aload_1
#    7: invokeinterface #3, 1  // Runnable.run:()V
#   12: return

# BootstrapMethods:
#   0: #27 REF_invokeStatic java/lang/invoke/LambdaMetafactory.metafactory:
#       (Ljava/lang/invoke/MethodHandles$Lookup;
#        Ljava/lang/String;
#        Ljava/lang/invoke/MethodType;
#        Ljava/lang/invoke/MethodType;
#        Ljava/lang/invoke/MethodHandle;
#        Ljava/lang/invoke/MethodType;)
#        Ljava/lang/invoke/CallSite;
#     Method arguments:
#       #28 ()V
#       #29 REF_invokeStatic LambdaDemo.lambda$test$0:()V
#       #28 ()V

# ëŒë‹¤ ë³¸ë¬¸ (ì»´íŒŒì¼ëŸ¬ ìƒì„± ë©”ì„œë“œ):
# private static void lambda$test$0();
#   Code:
#      0: getstatic #4   // System.out
#      3: ldc #5         // "Hello"
#      5: invokevirtual #6  // println
#      8: return
```

---

### 2. invokedynamic êµ¬ì¡°

```
invokedynamicì˜ 3ê°€ì§€ êµ¬ì„± ìš”ì†Œ:

1. Bootstrap Method (BSM)
   - í´ë˜ìŠ¤ ë¡œë”© ì‹œ í•œ ë²ˆë§Œ ì‹¤í–‰
   - CallSite ìƒì„±
   - ëŒë‹¤ì˜ ê²½ìš°: LambdaMetafactory.metafactory()

2. CallSite
   - ì‹¤ì œ í˜¸ì¶œ ëŒ€ìƒ (MethodHandle)
   - ìºì‹±ë¨ (ì²« í˜¸ì¶œ í›„ ì¬ì‚¬ìš©)
   
3. MethodHandle
   - ë©”ì„œë“œ ì°¸ì¡° (í•¨ìˆ˜ í¬ì¸í„°)
   - ëŒë‹¤ ë³¸ë¬¸ì„ ê°€ë¦¬í‚´

ì‹¤í–‰ íë¦„:

ì²« í˜¸ì¶œ:
  invokedynamic #2
  â†’ BSM(LambdaMetafactory.metafactory) í˜¸ì¶œ
  â†’ ëŒë‹¤ êµ¬í˜„ í´ë˜ìŠ¤ ë™ì  ìƒì„± (ì˜ˆ: LambdaDemo$$Lambda$1)
  â†’ CallSite ìƒì„± (ëŒë‹¤ ì¸ìŠ¤í„´ìŠ¤ ë°˜í™˜)
  â†’ CallSite ìºì‹±

ì´í›„ í˜¸ì¶œ:
  invokedynamic #2
  â†’ ìºì‹œëœ CallSite ì‚¬ìš©
  â†’ ëŒë‹¤ ì¸ìŠ¤í„´ìŠ¤ ì¦‰ì‹œ ë°˜í™˜
```

---

### 3. LambdaMetafactory ë™ì‘ ì›ë¦¬

```
LambdaMetafactory.metafactory() íŒŒë¼ë¯¸í„°:

1. caller (MethodHandles.Lookup)
   - í˜¸ì¶œì ì»¨í…ìŠ¤íŠ¸ (ì ‘ê·¼ ê¶Œí•œ)

2. invokedName (String)
   - ì¸í„°í˜ì´ìŠ¤ ë©”ì„œë“œëª… (ì˜ˆ: "run")

3. invokedType (MethodType)
   - ëŒë‹¤ íŒ©í† ë¦¬ ë©”ì„œë“œ ì‹œê·¸ë‹ˆì²˜
   - ì˜ˆ: ()Runnable (ì¸ì ì—†ìŒ, Runnable ë°˜í™˜)

4. samMethodType (MethodType)
   - í•¨ìˆ˜í˜• ì¸í„°í˜ì´ìŠ¤ ë©”ì„œë“œ ì‹œê·¸ë‹ˆì²˜
   - ì˜ˆ: ()V (Runnable.run)

5. implMethod (MethodHandle)
   - ëŒë‹¤ ë³¸ë¬¸ (ì»´íŒŒì¼ëŸ¬ ìƒì„± ë©”ì„œë“œ)
   - ì˜ˆ: LambdaDemo.lambda$test$0

6. instantiatedMethodType (MethodType)
   - ì‹¤ì œ ë©”ì„œë“œ íƒ€ì… (ì œë„¤ë¦­ erasure í›„)

ë™ì‘:
  1. íŒŒë¼ë¯¸í„° ê²€ì¦
  2. ë‚´ë¶€ í´ë˜ìŠ¤ ë™ì  ìƒì„± (ASM ì‚¬ìš©)
     ì˜ˆ: LambdaDemo$$Lambda$1 implements Runnable
  3. run() ë©”ì„œë“œê°€ lambda$test$0 í˜¸ì¶œí•˜ë„ë¡ êµ¬í˜„
  4. ì¸ìŠ¤í„´ìŠ¤ ìƒì„± í›„ ë°˜í™˜
```

---

### 4. ëŒë‹¤ ìº¡ì²˜ (Capture)

```java
int x = 10;
Runnable r = () -> System.out.println(x);
```

```
ìº¡ì²˜ ë³€ìˆ˜:
  ëŒë‹¤ ì™¸ë¶€ ë³€ìˆ˜ (x)ë¥¼ ëŒë‹¤ ë‚´ë¶€ì—ì„œ ì‚¬ìš©
  â†’ effectively finalì´ì–´ì•¼ í•¨

ë°”ì´íŠ¸ì½”ë“œ:

# test ë©”ì„œë“œ:
#    0: bipush 10
#    2: istore_1         // x = 10
#    3: iload_1
#    4: invokedynamic #2, 0  // InvokeDynamic #0:run:(I)Ljava/lang/Runnable;
#                             â†‘ xë¥¼ íŒŒë¼ë¯¸í„°ë¡œ ì „ë‹¬
#    9: astore_2
#   10: aload_2
#   11: invokeinterface #3, 1
#   16: return

# BootstrapMethods:
#   Method arguments:
#     ()V
#     REF_invokeStatic LambdaDemo.lambda$test$0:(I)V
#                                               â†‘ int íŒŒë¼ë¯¸í„° ì¶”ê°€
#     ()V

# ëŒë‹¤ ë³¸ë¬¸:
# private static void lambda$test$0(int);
#   Code:
#      0: getstatic #4   // System.out
#      3: iload_0        // ìº¡ì²˜ëœ x
#      4: invokevirtual #5  // println(int)
#      7: return

ë©”ì»¤ë‹ˆì¦˜:
  1. ìº¡ì²˜ ë³€ìˆ˜ë¥¼ invokedynamic íŒŒë¼ë¯¸í„°ë¡œ ì „ë‹¬
  2. ëŒë‹¤ ë©”ì„œë“œì— íŒŒë¼ë¯¸í„° ì¶”ê°€
  3. ìƒì„±ëœ ëŒë‹¤ ì¸ìŠ¤í„´ìŠ¤ì˜ í•„ë“œë¡œ ì €ì¥
```

---

### 5. ëŒë‹¤ vs ìµëª… í´ë˜ìŠ¤

```
ë°”ì´íŠ¸ì½”ë“œ ë¹„êµ:

ìµëª… í´ë˜ìŠ¤:
  class Outer {
      void test() {
          Runnable r = new Runnable() {
              public void run() { ... }
          };
      }
  }
  
  â†’ Outer$1.class íŒŒì¼ ìƒì„±
  â†’ ì»´íŒŒì¼ íƒ€ì„ì— êµ¬ì¡° ê³ ì •

ëŒë‹¤:
  class Outer {
      void test() {
          Runnable r = () -> { ... };
      }
  }
  
  â†’ ë³„ë„ .class íŒŒì¼ ì—†ìŒ
  â†’ ëŸ°íƒ€ì„ì— ë™ì  ìƒì„± (Outer$$Lambda$1)
  â†’ í´ë˜ìŠ¤ ë¡œë”ì—ë§Œ ì¡´ì¬ (íŒŒì¼ ì‹œìŠ¤í…œì— ì—†ìŒ)

ë©”ëª¨ë¦¬:
  ìµëª… í´ë˜ìŠ¤:
  ë§¤ë²ˆ new â†’ ìƒˆ ì¸ìŠ¤í„´ìŠ¤
  
  ëŒë‹¤ (ìº¡ì²˜ ì—†ìŒ):
  ì‹±ê¸€í†¤ì²˜ëŸ¼ ì¬ì‚¬ìš© ê°€ëŠ¥
  
  Runnable r1 = () -> System.out.println("Hello");
  Runnable r2 = () -> System.out.println("Hello");
  // r1 == r2 ì¼ ìˆ˜ë„ ìˆìŒ (êµ¬í˜„ ì˜ì¡´ì )
```

---

## ğŸ’» ì‹¤í—˜ìœ¼ë¡œ í™•ì¸í•˜ê¸°

### ì‹¤í—˜ 1: ëŒë‹¤ ë°”ì´íŠ¸ì½”ë“œ í™•ì¸

```java
import java.util.function.*;

public class LambdaTypes {
    public void test() {
        // ìº¡ì²˜ ì—†ìŒ
        Runnable r1 = () -> System.out.println("No capture");
        
        // ìº¡ì²˜ ìˆìŒ
        int x = 42;
        Runnable r2 = () -> System.out.println(x);
        
        // ë©”ì„œë“œ ì°¸ì¡°
        Runnable r3 = System.out::println;
    }
}
```

```bash
javap -c -v LambdaTypes.class

# r1 (ìº¡ì²˜ ì—†ìŒ):
# invokedynamic #2, 0  // run:()Ljava/lang/Runnable;
# Method arguments:
#   ()V
#   REF_invokeStatic lambda$test$0:()V
#   ()V

# r2 (ìº¡ì²˜ ìˆìŒ):
# invokedynamic #4, 0  // run:(I)Ljava/lang/Runnable;
#                       â†‘ int íŒŒë¼ë¯¸í„° (ìº¡ì²˜ëœ x)
# Method arguments:
#   ()V
#   REF_invokeStatic lambda$test$1:(I)V
#   ()V

# r3 (ë©”ì„œë“œ ì°¸ì¡°):
# getstatic System.out
# invokedynamic #5, 0  // run:(Ljava/io/PrintStream;)Ljava/lang/Runnable;
# Method arguments:
#   ()V
#   REF_invokeVirtual PrintStream.println:()V
#   ()V
```

---

### ì‹¤í—˜ 2: ëŸ°íƒ€ì„ ìƒì„± í´ë˜ìŠ¤ í™•ì¸

```java
public class LambdaClassDemo {
    public static void main(String[] args) {
        Runnable r = () -> System.out.println("Hello");
        
        System.out.println("Lambda class: " + r.getClass().getName());
        System.out.println("Declared methods:");
        for (var m : r.getClass().getDeclaredMethods()) {
            System.out.println("  " + m);
        }
    }
}
```

```bash
# ì¶œë ¥:
# Lambda class: LambdaClassDemo$$Lambda$1/0x0000000800c00400
#               â†‘ ë™ì  ìƒì„±ëœ í´ë˜ìŠ¤ (íŒŒì¼ ì—†ìŒ)
# Declared methods:
#   public void LambdaClassDemo$$Lambda$1.run()
```

---

### ì‹¤í—˜ 3: ëŒë‹¤ ì¬ì‚¬ìš© í™•ì¸

```java
public class LambdaSingleton {
    public static void main(String[] args) {
        // ìº¡ì²˜ ì—†ëŠ” ëŒë‹¤
        Runnable r1 = () -> System.out.println("A");
        Runnable r2 = () -> System.out.println("A");
        System.out.println("r1 == r2: " + (r1 == r2));  // true ê°€ëŠ¥
        
        // ìº¡ì²˜ ìˆëŠ” ëŒë‹¤
        int x = 10;
        Runnable r3 = () -> System.out.println(x);
        Runnable r4 = () -> System.out.println(x);
        System.out.println("r3 == r4: " + (r3 == r4));  // false (ìƒˆ ì¸ìŠ¤í„´ìŠ¤)
    }
}
```

---

### ì‹¤í—˜ 4: -Djdk.internal.lambda.dumpProxyClasses

```bash
# ëŒë‹¤ í´ë˜ìŠ¤ë¥¼ íŒŒì¼ë¡œ ë¤í”„
java -Djdk.internal.lambda.dumpProxyClasses=. LambdaDemo

# ìƒì„±ëœ íŒŒì¼:
# LambdaDemo$$Lambda$1.class

# ë””ì»´íŒŒì¼:
javap -c LambdaDemo\$\$Lambda\$1.class

# ì¶œë ¥:
# final class LambdaDemo$$Lambda$1 implements Runnable {
#   public void run();
#     Code:
#        0: invokestatic LambdaDemo.lambda$test$0:()V
#        3: return
# }
```

---

## âš¡ ì‹¤ë¬´ ì„íŒ©íŠ¸

### ëŒë‹¤ ì„±ëŠ¥ ìµœì í™”

```
ìº¡ì²˜ ì—†ëŠ” ëŒë‹¤:
  Supplier<String> s1 = () -> "Hello";
  Supplier<String> s2 = () -> "Hello";
  
  â†’ JVMì´ ì‹±ê¸€í†¤ìœ¼ë¡œ ìµœì í™” ê°€ëŠ¥
  â†’ ë©”ëª¨ë¦¬ íš¨ìœ¨ì 

ìº¡ì²˜ ìˆëŠ” ëŒë‹¤:
  int x = 10;
  Supplier<Integer> s = () -> x;
  
  â†’ ë§¤ë²ˆ ìƒˆ ì¸ìŠ¤í„´ìŠ¤ ìƒì„±
  â†’ ìº¡ì²˜ ë³€ìˆ˜ë¥¼ í•„ë“œë¡œ ì €ì¥
  
ë£¨í”„ ë‚´ ëŒë‹¤ (ìº¡ì²˜ ìˆìŒ):
  for (int i = 0; i < 1000; i++) {
      int x = i;
      list.add(() -> x);  // 1000ê°œ ì¸ìŠ¤í„´ìŠ¤ ìƒì„±
  }
  
  â†’ ë©”ëª¨ë¦¬ ì••ë°•
  
ìµœì í™”:
  ê°€ëŠ¥í•˜ë©´ ìº¡ì²˜ ì—†ëŠ” ëŒë‹¤ ì‚¬ìš©
  ë˜ëŠ” ë©”ì„œë“œ ì°¸ì¡°ë¡œ ëŒ€ì²´
```

### invokedynamicì˜ ë¯¸ë˜ í™•ì¥ì„±

```
JDK ë²„ì „ë³„ ê°œì„ :

Java 8:
  LambdaMetafactory ê¸°ë³¸ êµ¬í˜„
  â†’ ë‚´ë¶€ í´ë˜ìŠ¤ ë™ì  ìƒì„±

Java 9+:
  String Concatenationë„ invokedynamic ì‚¬ìš©
  "Hello " + name â†’ invokedynamic
  
Java 17+:
  Switch í‘œí˜„ì‹ ìµœì í™”
  Pattern Matching

ì¥ì :
  ë°”ì´íŠ¸ì½”ë“œëŠ” invokedynamicë§Œ ìœ ì§€
  â†’ JVM ì—…ê·¸ë ˆì´ë“œ ì‹œ ìë™ìœ¼ë¡œ ìµœì í™” ì ìš©
  â†’ ì¬ì»´íŒŒì¼ ë¶ˆí•„ìš”
```

### MethodHandle vs Reflection

```
Reflection:
  Method m = String.class.getMethod("length");
  int len = (int) m.invoke("hello");
  
  â†’ ëŠë¦¼ (íƒ€ì… ì²´í¬, boxing)
  â†’ ë³´ì•ˆ ê²€ì‚¬

MethodHandle:
  MethodHandles.Lookup lookup = MethodHandles.lookup();
  MethodHandle mh = lookup.findVirtual(String.class, "length", 
                                       MethodType.methodType(int.class));
  int len = (int) mh.invokeExact("hello");
  
  â†’ ë¹ ë¦„ (JIT ì¸ë¼ì¸ ê°€ëŠ¥)
  â†’ invokedynamicì˜ ê¸°ë°˜

ì„±ëŠ¥:
  Reflection: 100 ns
  MethodHandle: 1 ns (JIT í›„)
  â†’ 100ë°° ì°¨ì´
```

---

## ğŸš« í”í•œ ì˜¤í•´

### "ëŒë‹¤ëŠ” ìµëª… í´ë˜ìŠ¤ì˜ ë¬¸ë²• ì„¤íƒ•ì´ë‹¤"

```
âŒ ì˜ëª»ëœ ì´í•´:
  ëŒë‹¤ëŠ” ìµëª… í´ë˜ìŠ¤ë¥¼ ê°„ê²°í•˜ê²Œ ì“´ ê²ƒì¼ ë¿ì´ë‹¤.

âœ… ì‹¤ì œ:
  ì™„ì „íˆ ë‹¤ë¥¸ ë©”ì»¤ë‹ˆì¦˜
  
ìµëª… í´ë˜ìŠ¤:
  - ì»´íŒŒì¼ íƒ€ì„ì— í´ë˜ìŠ¤ íŒŒì¼ ìƒì„±
  - í•­ìƒ ìƒˆ ê°ì²´ (new)
  - thisëŠ” ìµëª… í´ë˜ìŠ¤ ì¸ìŠ¤í„´ìŠ¤

ëŒë‹¤:
  - ëŸ°íƒ€ì„ì— ë™ì  ìƒì„± (invokedynamic)
  - ì¬ì‚¬ìš© ê°€ëŠ¥ (ìº¡ì²˜ ì—†ëŠ” ê²½ìš°)
  - thisëŠ” ì™¸ë¶€ í´ë˜ìŠ¤ (enclosing class)

ì˜ˆ:
  class Outer {
      void test() {
          // ìµëª… í´ë˜ìŠ¤
          Runnable r1 = new Runnable() {
              public void run() {
                  System.out.println(this.getClass());  // Outer$1
              }
          };
          
          // ëŒë‹¤
          Runnable r2 = () -> {
              System.out.println(this.getClass());  // Outer
          };
      }
  }
```

### "ëŒë‹¤ëŠ” í•­ìƒ ìµëª… í´ë˜ìŠ¤ë³´ë‹¤ ë¹ ë¥´ë‹¤"

```
âŒ ì˜ëª»ëœ ì´í•´:
  ëŒë‹¤ë¥¼ ì“°ë©´ ë¬´ì¡°ê±´ ì„±ëŠ¥ì´ ì¢‹ì•„ì§„ë‹¤.

âœ… ì‹¤ì œ:
  Warm-up í›„ì—ëŠ” ê±°ì˜ ë™ì¼
  
ë²¤ì¹˜ë§ˆí¬:
  ìµëª… í´ë˜ìŠ¤: 1.0 ns (JIT ì¸ë¼ì¸ í›„)
  ëŒë‹¤:       1.0 ns (JIT ì¸ë¼ì¸ í›„)
  
ì°¨ì´ì :
  - í´ë˜ìŠ¤ ë¡œë”© ì‹œê°„: ëŒë‹¤ê°€ ë¹ ë¦„ (ë™ì  ìƒì„±)
  - ë©”ëª¨ë¦¬: ëŒë‹¤ê°€ ì ìŒ (ì¬ì‚¬ìš© ê°€ëŠ¥)
  - ì½”ë“œ í¬ê¸°: ëŒë‹¤ê°€ ì‘ìŒ (.class íŒŒì¼ ì—†ìŒ)
  
  ì‹¤í–‰ ì†ë„ëŠ” ê±°ì˜ ë™ì¼
```

### "invokedynamicì€ í•­ìƒ ëŠë¦¬ë‹¤"

```
âŒ ì˜ëª»ëœ ì´í•´:
  ë™ì  í˜¸ì¶œì´ë¼ ëŠë¦´ ê²ƒì´ë‹¤.

âœ… ì‹¤ì œ:
  ì²« í˜¸ì¶œë§Œ ëŠë¦¼, ì´í›„ëŠ” ë¹ ë¦„
  
ë¹„ìš©:
  ì²« í˜¸ì¶œ:
  - Bootstrap Method ì‹¤í–‰ (~100 us)
  - í´ë˜ìŠ¤ ë™ì  ìƒì„±
  - CallSite ìƒì„±
  â†’ ëŠë¦¼
  
  ì´í›„ í˜¸ì¶œ:
  - CallSite ìºì‹œ ì‚¬ìš©
  - JIT ì¸ë¼ì¸ ê°€ëŠ¥
  â†’ invokevirtualê³¼ ë™ì¼í•˜ê±°ë‚˜ ë” ë¹ ë¦„

ê¶Œì¥:
  Hot Pathì—ì„œ ëŒë‹¤ ì‚¬ìš© OK
  ë‹¨, ë£¨í”„ ë°–ìœ¼ë¡œ ì´ë™ (ì¬ì‚¬ìš©)
```

---

## ğŸ“Œ í•µì‹¬ ì •ë¦¬

```
ëŒë‹¤ ë°”ì´íŠ¸ì½”ë“œ
  invokedynamic ëª…ë ¹ì–´ ì‚¬ìš©
  BootstrapMethod: LambdaMetafactory.metafactory
  ëŒë‹¤ ë³¸ë¬¸: ì»´íŒŒì¼ëŸ¬ ìƒì„± static ë©”ì„œë“œ

invokedynamic êµ¬ì¡°
  Bootstrap Method (ì²« í˜¸ì¶œ ì‹œ ì‹¤í–‰)
  â†’ CallSite ìƒì„± (ìºì‹±)
  â†’ MethodHandle (ì‹¤ì œ í˜¸ì¶œ ëŒ€ìƒ)

LambdaMetafactory
  ëŸ°íƒ€ì„ì— ëŒë‹¤ êµ¬í˜„ í´ë˜ìŠ¤ ë™ì  ìƒì„±
  ì˜ˆ: Outer$$Lambda$1 implements Runnable
  ASMìœ¼ë¡œ ë°”ì´íŠ¸ì½”ë“œ ìƒì„±

ìº¡ì²˜ (Capture)
  ì™¸ë¶€ ë³€ìˆ˜ë¥¼ ëŒë‹¤ ë‚´ë¶€ì—ì„œ ì‚¬ìš©
  â†’ invokedynamic íŒŒë¼ë¯¸í„°ë¡œ ì „ë‹¬
  â†’ ëŒë‹¤ ì¸ìŠ¤í„´ìŠ¤ í•„ë“œë¡œ ì €ì¥
  â†’ effectively final í•„ìˆ˜

ëŒë‹¤ vs ìµëª… í´ë˜ìŠ¤
  ëŒë‹¤: ë™ì  ìƒì„±, ì¬ì‚¬ìš© ê°€ëŠ¥, this=ì™¸ë¶€
  ìµëª…: ì»´íŒŒì¼ íƒ€ì„ ìƒì„±, í•­ìƒ ìƒˆ ê°ì²´, this=ìì‹ 

ì„±ëŠ¥
  ì²« í˜¸ì¶œ: Bootstrap Method ë¹„ìš©
  ì´í›„: ìºì‹œ ì‚¬ìš©, JIT ì¸ë¼ì¸ ê°€ëŠ¥
  Warm-up í›„: ìµëª… í´ë˜ìŠ¤ì™€ ë™ì¼

ë¯¸ë˜ í™•ì¥ì„±
  ë°”ì´íŠ¸ì½”ë“œëŠ” invokedynamicë§Œ
  JVM ì—…ê·¸ë ˆì´ë“œ ì‹œ ìë™ ìµœì í™”
  ì¬ì»´íŒŒì¼ ë¶ˆí•„ìš”
```

---

## ğŸ¤” ìƒê°í•´ë³¼ ë¬¸ì œ

**Q1.** ë‹¤ìŒ ë‘ ëŒë‹¤ì˜ ë°”ì´íŠ¸ì½”ë“œ ì°¨ì´ë¥¼ ì„¤ëª…í•˜ë¼. invokedynamic íŒŒë¼ë¯¸í„°ì™€ ëŒë‹¤ ë©”ì„œë“œ ì‹œê·¸ë‹ˆì²˜ì— ì´ˆì ì„ ë§ì¶°ë¼.

```java
// ëŒë‹¤ 1
Runnable r1 = () -> System.out.println("Hello");

// ëŒë‹¤ 2
int x = 42;
Runnable r2 = () -> System.out.println(x);
```

**Q2.** ì™œ ëŒë‹¤ëŠ” `invokedynamic`ì„ ì‚¬ìš©í•˜ëŠ”ê°€? ì»´íŒŒì¼ íƒ€ì„ì— ìµëª… í´ë˜ìŠ¤ë¡œ ë³€í™˜í•˜ì§€ ì•ŠëŠ” ì´ìœ ë¥¼ 3ê°€ì§€ ì´ìƒ ì„¤ëª…í•˜ë¼.

**Q3.** ë‹¤ìŒ ì½”ë“œì˜ ì„±ëŠ¥ ë¬¸ì œë¥¼ ì§€ì í•˜ê³  ê°œì„  ë°©ë²•ì„ ì œì‹œí•˜ë¼.

```java
for (int i = 0; i < 10000; i++) {
    int x = i;
    executor.submit(() -> process(x));
}
```

> ğŸ’¡ **í•´ì„¤**
>
> **Q1.** ëŒë‹¤ 1 (ìº¡ì²˜ ì—†ìŒ): `invokedynamic #2, 0 // run:()Ljava/lang/Runnable;` â€” íŒŒë¼ë¯¸í„° ì—†ìŒ. ëŒë‹¤ ë©”ì„œë“œ: `lambda$test$0:()V` â€” íŒŒë¼ë¯¸í„° ì—†ìŒ. ì‹±ê¸€í†¤ì²˜ëŸ¼ ì¬ì‚¬ìš© ê°€ëŠ¥. ëŒë‹¤ 2 (ìº¡ì²˜ ìˆìŒ): `invokedynamic #4, 0 // run:(I)Ljava/lang/Runnable;` â€” int íŒŒë¼ë¯¸í„° (x=42). ëŒë‹¤ ë©”ì„œë“œ: `lambda$test$1:(I)V` â€” int íŒŒë¼ë¯¸í„° ë°›ìŒ. ë§¤ë²ˆ ìƒˆ ì¸ìŠ¤í„´ìŠ¤ ìƒì„± (x ê°’ì„ í•„ë“œë¡œ ì €ì¥). í•µì‹¬: ìº¡ì²˜ ë³€ìˆ˜ëŠ” invokedynamic íŒŒë¼ë¯¸í„°ë¡œ ì „ë‹¬ â†’ ëŒë‹¤ ì¸ìŠ¤í„´ìŠ¤ ìƒì„± ì‹œ í•„ë“œë¡œ ì €ì¥.
>
> **Q2.** â‘  ë¯¸ë˜ í™•ì¥ì„± â€” JVMì´ ëŒë‹¤ êµ¬í˜„ ë°©ì‹ì„ ììœ ë¡­ê²Œ ë³€ê²½ ê°€ëŠ¥. Java 8ì€ ë‚´ë¶€ í´ë˜ìŠ¤ ìƒì„±, ë¯¸ë˜ì—ëŠ” ë” ë‚˜ì€ ë°©ë²• ì ìš© ê°€ëŠ¥ (ë°”ì´íŠ¸ì½”ë“œ ì¬ì»´íŒŒì¼ ë¶ˆí•„ìš”). â‘¡ ë©”ëª¨ë¦¬ íš¨ìœ¨ â€” ìº¡ì²˜ ì—†ëŠ” ëŒë‹¤ëŠ” ì‹±ê¸€í†¤ì²˜ëŸ¼ ì¬ì‚¬ìš© ê°€ëŠ¥. ìµëª… í´ë˜ìŠ¤ëŠ” ë§¤ë²ˆ newë¡œ ìƒˆ ê°ì²´. â‘¢ í´ë˜ìŠ¤ íŒŒì¼ ìµœì†Œí™” â€” ìµëª… í´ë˜ìŠ¤ëŠ” Outer$1.class íŒŒì¼ ìƒì„±. ëŒë‹¤ëŠ” ëŸ°íƒ€ì„ ë™ì  ìƒì„± (íŒŒì¼ ì—†ìŒ). â‘£ ìµœì í™” ê¸°íšŒ â€” invokedynamicì˜ Bootstrap Methodê°€ ìµœì í™”ëœ êµ¬í˜„ ì„ íƒ (ì˜ˆ: ìƒíƒœ ì—†ìœ¼ë©´ ì‹±ê¸€í†¤, ìˆìœ¼ë©´ ìƒˆ ì¸ìŠ¤í„´ìŠ¤). â‘¤ íƒ€ì… ì¶”ë¡  â€” ëŒë‹¤ëŠ” íƒ€ì… ì†Œê±° í›„ì—ë„ ì •ë³´ ìœ ì§€ ê°€ëŠ¥ (MethodType).
>
> **Q3.** ë¬¸ì œ: ë£¨í”„ 10,000íšŒë§ˆë‹¤ ìº¡ì²˜ ìˆëŠ” ëŒë‹¤ ìƒì„± â†’ 10,000ê°œ ëŒë‹¤ ì¸ìŠ¤í„´ìŠ¤ + 10,000ë²ˆ invokedynamic ì²« í˜¸ì¶œ ì˜¤ë²„í—¤ë“œ (ê° ië§ˆë‹¤ ë‹¤ë¥¸ CallSite). ê°œì„ : â‘  ëŒë‹¤ë¥¼ ë£¨í”„ ë°–ìœ¼ë¡œ ì´ë™ (ë¶ˆê°€ëŠ¥, xê°€ ë£¨í”„ ë³€ìˆ˜). â‘¡ ìµëª… í´ë˜ìŠ¤ ë˜ëŠ” ë³„ë„ í´ë˜ìŠ¤ ì‚¬ìš© â€” `executor.submit(new ProcessTask(i))` where `ProcessTask implements Runnable`. â‘¢ ë©”ì„œë“œ ì°¸ì¡°ë¡œ ë³€ê²½ (ê°€ëŠ¥í•˜ë‹¤ë©´). â‘£ ë°°ì¹˜ ì²˜ë¦¬ â€” 10,000ê°œë¥¼ ëª¨ì•„ì„œ í•œ ë²ˆì— ì²˜ë¦¬. í•µì‹¬: ìº¡ì²˜ ìˆëŠ” ëŒë‹¤ë¥¼ ëŒ€ëŸ‰ ìƒì„±í•˜ë©´ ë©”ëª¨ë¦¬ì™€ GC ì••ë°•. ê°€ëŠ¥í•˜ë©´ ì¬ì‚¬ìš© ê°€ëŠ¥í•œ êµ¬ì¡°ë¡œ ë³€ê²½.

---

## ğŸ“š ì°¸ê³  ìë£Œ

- [JEP 126 â€” Lambda Expressions & Virtual Extension Methods](https://openjdk.org/jeps/126)
- [Translation of Lambda Expressions (Brian Goetz)](http://cr.openjdk.java.net/~briangoetz/lambda/lambda-translation.html)
- [JVMS Â§4.7.23 â€” BootstrapMethods Attribute](https://docs.oracle.com/javase/specs/jvms/se21/html/jvms-4.html#jvms-4.7.23)

---

<div align="center">

**[â¬…ï¸ ì´ì „: Exception Handling Bytecode](./05-exception-handling-bytecode.md)** | **[ë‹¤ìŒ: Bytecode Manipulation (ASM) â¡ï¸](./07-bytecode-manipulation-asm.md)**

</div>
